Workbook

Sheet Synthèse hebdo
A1: Synthèse des évaluations par collaborateur et par semaine
A2: Nb docs = documents traités dans la semaine ; Note moy. = moyenne des notes /100 des documents évalués (cellule vide = aucun document). Calculé par formules à partir de l'onglet « Détail ».
A4: Année | B4: Semaine | C4: Période (lun.–dim.) | D4: Hafssa BENCHRIF | F4: Hiba LISSAOUI | H4: Imad RMAIDI | J4: Mohamed HAMDANI | L4: Youssef | N4: Équipe
D5: Nb docs | E5: Note moy. | F5: Nb docs | G5: Note moy. | H5: Nb docs | I5: Note moy. | J5: Nb docs | K5: Note moy. | L5: Nb docs | M5: Note moy. | N5: Nb docs | O5: Note moy.
A6: 2025 | B6: 51 | C6: 15/12/2025 – 21/12/2025 | D6: =COUNTIFS(Détail!$A:$A,"Hafssa BENCHRIF",Détail!$B:$B,$A6,Détail!$C:$C,$B6,Détail!$E:$E,"<>(à saisir)") | E6: =IFERROR(AVERAGEIFS(Détail!$I:$I,Détail!$A:$A,"Hafssa BENCHRIF",Détail!$B:$B,$A6,Détail!$C:$C,$B6),"") | F6: =COUNTIFS(Détail!$A:$A,"Hiba LISSAOUI",Détail!$B:$B,$A6,Détail!$C:$C,$B6,Détail!$E:$E,"<>(à saisir)") | G6: =IFERROR(AVERAGEIFS(Détail!$I:$I,Détail!$A:$A,"Hiba LISSAOUI",Détail!$B:$B,$A6,Détail!$C:$C,$B6),"") | H6: =COUNTIFS(Détail!$A:$A,"Imad RMAIDI",Détail!$B:$B,$A6,Détail!$C:$C,$B6,Détail!$E:$E,"<>(à saisir)") | I6: =IFERROR(AVERAGEIFS(Détail!$I:$I,Détail!$A:$A,"Imad RMAIDI",Détail!$B:$B,$A6,Détail!$C:$C,$B6),"") | J6: =COUNTIFS(Détail!$A:$A,"Mohamed HAMDANI",Détail!$B:$B,$A6,Détail!$C:$C,$B6,Détail!$E:$E,"<>(à saisir)") | K6: =IFERROR(AVERAGEIFS(Détail!$I:$I,Détail!$A:$A,"Mohamed HAMDANI",Détail!$B:$B,$A6,Détail!$C:$C,$B6),"") | L6: =COUNTIFS(Détail!$A:$A,"Youssef",Détail!$B:$B,$A6,Détail!$C:$C,$B6,Détail!$E:$E,"<>(à saisir)") | M6: =IFERROR(AVERAGEIFS(Détail!$I:$I,Détail!$A:$A,"Youssef",Détail!$B:$B,$A6,Détail!$C:$C,$B6),"") | N6: =COUNTIFS(Détail!$B:$B,$A6,Détail!$C:$C,$B6,Détail!$E:$E,"<>(à saisir)") | O6: =IFERROR(AVERAGEIFS(Détail!$I:$I,Détail!$B:$B,$A6,Détail!$C:$C,$B6),"")
A7: 2025 | B7: 52 | C7: 22/12/2025 – 28/12/2025 | D7: =COUNTIFS(Détail!$A:$A,"Hafssa BENCHRIF",Détail!$B:$B,$A7,Détail!$C:$C,$B7,Détail!$E:$E,"<>(à saisir)") | E7: =IFERROR(AVERAGEIFS(Détail!$I:$I,Détail!$A:$A,"Hafssa BENCHRIF",Détail!$B:$B,$A7,Détail!$C:$C,$B7),"") | F7: =COUNTIFS(Détail!$A:$A,"Hiba LISSAOUI",Détail!$B:$B,$A7,Détail!$C:$C,$B7,Détail!$E:$E,"<>(à saisir)") | G7: =IFERROR(AVERAGEIFS(Détail!$I:$I,Détail!$A:$A,"Hiba LISSAOUI",Détail!$B:$B,$A7,Détail!$C:$C,$B7),"") | H7: =COUNTIFS(Détail!$A:$A,"Imad RMAIDI",Détail!$B:$B,$A7,Détail!$C:$C,$B7,Détail!$E:$E,"<>(à saisir)") | I7: =IFERROR(AVERAGEIFS(Détail!$I:$I,Détail!$A:$A,"Imad RMAIDI",Détail!$B:$B,$A7,Détail!$C:$C,$B7),"") | J7: =COUNTIFS(Détail!$A:$A,"Mohamed HAMDANI",Détail!$B:$B,$A7,Détail!$C:$C,$B7,Détail!$E:$E,"<>(à saisir)") | K7: =IFERROR(AVERAGEIFS(Détail!$I:$I,Détail!$A:$A,"Mohamed HAMDANI",Détail!$B:$B,$A7,Détail!$C:$C,$B7),"") | L7: =COUNTIFS(Détail!$A:$A,"Youssef",Détail!$B:$B,$A7,Détail!$C:$C,$B7,Détail!$E:$E,"<>(à saisir)") | M7: =IFERROR(AVERAGEIFS(Détail!$I:$I,Détail!$A:$A,"Youssef",Détail!$B:$B,$A7,Détail!$C:$C,$B7),"") | N7: =COUNTIFS(Détail!$B:$B,$A7,Détail!$C:$C,$B7,Détail!$E:$E,"<>(à saisir)") | O7: =IFERROR(AVERAGEIFS(Détail!$I:$I,Détail!$B:$B,$A7,Détail!$C:$C,$B7),"")
A8: 2026 | B8: 1 | C8: 29/12/2025 – 04/01/2026 | D8: =COUNTIFS(Détail!$A:$A,"Hafssa BENCHRIF",Détail!$B:$B,$A8,Détail!$C:$C,$B8,Détail!$E:$E,"<>(à saisir)") | E8: =IFERROR(AVERAGEIFS(Détail!$I:$I,Détail!$A:$A,"Hafssa BENCHRIF",Détail!$B:$B,$A8,Détail!$C:$C,$B8),"") | F8: =COUNTIFS(Détail!$A:$A,"Hiba LISSAOUI",Détail!$B:$B,$A8,Détail!$C:$C,$B8,Détail!$E:$E,"<>(à saisir)") | G8: =IFERROR(AVERAGEIFS(Détail!$I:$I,Détail!$A:$A,"Hiba LISSAOUI",Détail!$B:$B,$A8,Détail!$C:$C,$B8),"") | H8: =COUNTIFS(Détail!$A:$A,"Imad RMAIDI",Détail!$B:$B,$A8,Détail!$C:$C,$B8,Détail!$E:$E,"<>(à saisir)") | I8: =IFERROR(AVERAGEIFS(Détail!$I:$I,Détail!$A:$A,"Imad RMAIDI",Détail!$B:$B,$A8,Détail!$C:$C,$B8),"") | J8: =COUNTIFS(Détail!$A:$A,"Mohamed HAMDANI",Détail!$B:$B,$A8,Détail!$C:$C,$B8,Détail!$E:$E,"<>(à saisir)") | K8: =IFERROR(AVERAGEIFS(Détail!$I:$I,Détail!$A:$A,"Mohamed HAMDANI",Détail!$B:$B,$A8,Détail!$C:$C,$B8),"") | L8: =COUNTIFS(Détail!$A:$A,"Youssef",Détail!$B:$B,$A8,Détail!$C:$C,$B8,Détail!$E:$E,"<>(à saisir)") | M8: =IFERROR(AVERAGEIFS(Détail!$I:$I,Détail!$A:$A,"Youssef",Détail!$B:$B,$A8,Détail!$C:$C,$B8),"") | N8: =COUNTIFS(Détail!$B:$B,$A8,Détail!$C:$C,$B8,Détail!$E:$E,"<>(à saisir)") | O8: =IFERROR(AVERAGEIFS(Détail!$I:$I,Détail!$B:$B,$A8,Détail!$C:$C,$B8),"")
A9: 2026 | B9: 2 | C9: 05/01/2026 – 11/01/2026 | D9: =COUNTIFS(Détail!$A:$A,"Hafssa BENCHRIF",Détail!$B:$B,$A9,Détail!$C:$C,$B9,Détail!$E:$E,"<>(à saisir)") | E9: =IFERROR(AVERAGEIFS(Détail!$I:$I,Détail!$A:$A,"Hafssa BENCHRIF",Détail!$B:$B,$A9,Détail!$C:$C,$B9),"") | F9: =COUNTIFS(Détail!$A:$A,"Hiba LISSAOUI",Détail!$B:$B,$A9,Détail!$C:$C,$B9,Détail!$E:$E,"<>(à saisir)") | G9: =IFERROR(AVERAGEIFS(Détail!$I:$I,Détail!$A:$A,"Hiba LISSAOUI",Détail!$B:$B,$A9,Détail!$C:$C,$B9),"") | H9: =COUNTIFS(Détail!$A:$A,"Imad RMAIDI",Détail!$B:$B,$A9,Détail!$C:$C,$B9,Détail!$E:$E,"<>(à saisir)") | I9: =IFERROR(AVERAGEIFS(Détail!$I:$I,Détail!$A:$A,"Imad RMAIDI",Détail!$B:$B,$A9,Détail!$C:$C,$B9),"") | J9: =COUNTIFS(Détail!$A:$A,"Mohamed HAMDANI",Détail!$B:$B,$A9,Détail!$C:$C,$B9,Détail!$E:$E,"<>(à saisir)") | K9: =IFERROR(AVERAGEIFS(Détail!$I:$I,Détail!$A:$A,"Mohamed HAMDANI",Détail!$B:$B,$A9,Détail!$C:$C,$B9),"") | L9: =COUNTIFS(Détail!$A:$A,"Youssef",Détail!$B:$B,$A9,Détail!$C:$C,$B9,Détail!$E:$E,"<>(à saisir)") | M9: =IFERROR(AVERAGEIFS(Détail!$I:$I,Détail!$A:$A,"Youssef",Détail!$B:$B,$A9,Détail!$C:$C,$B9),"") | N9: =COUNTIFS(Détail!$B:$B,$A9,Détail!$C:$C,$B9,Détail!$E:$E,"<>(à saisir)") | O9: =IFERROR(AVERAGEIFS(Détail!$I:$I,Détail!$B:$B,$A9,Détail!$C:$C,$B9),"")
A10: 2026 | B10: 3 | C10: 12/01/2026 – 18/01/2026 | D10: =COUNTIFS(Détail!$A:$A,"Hafssa BENCHRIF",Détail!$B:$B,$A10,Détail!$C:$C,$B10,Détail!$E:$E,"<>(à saisir)") | E10: =IFERROR(AVERAGEIFS(Détail!$I:$I,Détail!$A:$A,"Hafssa BENCHRIF",Détail!$B:$B,$A10,Détail!$C:$C,$B10),"") | F10: =COUNTIFS(Détail!$A:$A,"Hiba LISSAOUI",Détail!$B:$B,$A10,Détail!$C:$C,$B10,Détail!$E:$E,"<>(à saisir)") | G10: =IFERROR(AVERAGEIFS(Détail!$I:$I,Détail!$A:$A,"Hiba LISSAOUI",Détail!$B:$B,$A10,Détail!$C:$C,$B10),"") | H10: =COUNTIFS(Détail!$A:$A,"Imad RMAIDI",Détail!$B:$B,$A10,Détail!$C:$C,$B10,Détail!$E:$E,"<>(à saisir)") | I10: =IFERROR(AVERAGEIFS(Détail!$I:$I,Détail!$A:$A,"Imad RMAIDI",Détail!$B:$B,$A10,Détail!$C:$C,$B10),"") | J10: =COUNTIFS(Détail!$A:$A,"Mohamed HAMDANI",Détail!$B:$B,$A10,Détail!$C:$C,$B10,Détail!$E:$E,"<>(à saisir)") | K10: =IFERROR(AVERAGEIFS(Détail!$I:$I,Détail!$A:$A,"Mohamed HAMDANI",Détail!$B:$B,$A10,Détail!$C:$C,$B10),"") | L10: =COUNTIFS(Détail!$A:$A,"Youssef",Détail!$B:$B,$A10,Détail!$C:$C,$B10,Détail!$E:$E,"<>(à saisir)") | M10: =IFERROR(AVERAGEIFS(Détail!$I:$I,Détail!$A:$A,"Youssef",Détail!$B:$B,$A10,Détail!$C:$C,$B10),"") | N10: =COUNTIFS(Détail!$B:$B,$A10,Détail!$C:$C,$B10,Détail!$E:$E,"<>(à saisir)") | O10: =IFERROR(AVERAGEIFS(Détail!$I:$I,Détail!$B:$B,$A10,Détail!$C:$C,$B10),"")
A11: 2026 | B11: 4 | C11: 19/01/2026 – 25/01/2026 | D11: =COUNTIFS(Détail!$A:$A,"Hafssa BENCHRIF",Détail!$B:$B,$A11,Détail!$C:$C,$B11,Détail!$E:$E,"<>(à saisir)") | E11: =IFERROR(AVERAGEIFS(Détail!$I:$I,Détail!$A:$A,"Hafssa BENCHRIF",Détail!$B:$B,$A11,Détail!$C:$C,$B11),"") | F11: =COUNTIFS(Détail!$A:$A,"Hiba LISSAOUI",Détail!$B:$B,$A11,Détail!$C:$C,$B11,Détail!$E:$E,"<>(à saisir)") | G11: =IFERROR(AVERAGEIFS(Détail!$I:$I,Détail!$A:$A,"Hiba LISSAOUI",Détail!$B:$B,$A11,Détail!$C:$C,$B11),"") | H11: =COUNTIFS(Détail!$A:$A,"Imad RMAIDI",Détail!$B:$B,$A11,Détail!$C:$C,$B11,Détail!$E:$E,"<>(à saisir)") | I11: =IFERROR(AVERAGEIFS(Détail!$I:$I,Détail!$A:$A,"Imad RMAIDI",Détail!$B:$B,$A11,Détail!$C:$C,$B11),"") | J11: =COUNTIFS(Détail!$A:$A,"Mohamed HAMDANI",Détail!$B:$B,$A11,Détail!$C:$C,$B11,Détail!$E:$E,"<>(à saisir)") | K11: =IFERROR(AVERAGEIFS(Détail!$I:$I,Détail!$A:$A,"Mohamed HAMDANI",Détail!$B:$B,$A11,Détail!$C:$C,$B11),"") | L11: =COUNTIFS(Détail!$A:$A,"Youssef",Détail!$B:$B,$A11,Détail!$C:$C,$B11,Détail!$E:$E,"<>(à saisir)") | M11: =IFERROR(AVERAGEIFS(Détail!$I:$I,Détail!$A:$A,"Youssef",Détail!$B:$B,$A11,Détail!$C:$C,$B11),"") | N11: =COUNTIFS(Détail!$B:$B,$A11,Détail!$C:$C,$B11,Détail!$E:$E,"<>(à saisir)") | O11: =IFERROR(AVERAGEIFS(Détail!$I:$I,Détail!$B:$B,$A11,Détail!$C:$C,$B11),"")
A12: 2026 | B12: 5 | C12: 26/01/2026 – 01/02/2026 | D12: =COUNTIFS(Détail!$A:$A,"Hafssa BENCHRIF",Détail!$B:$B,$A12,Détail!$C:$C,$B12,Détail!$E:$E,"<>(à saisir)") | E12: =IFERROR(AVERAGEIFS(Détail!$I:$I,Détail!$A:$A,"Hafssa BENCHRIF",Détail!$B:$B,$A12,Détail!$C:$C,$B12),"") | F12: =COUNTIFS(Détail!$A:$A,"Hiba LISSAOUI",Détail!$B:$B,$A12,Détail!$C:$C,$B12,Détail!$E:$E,"<>(à saisir)") | G12: =IFERROR(AVERAGEIFS(Détail!$I:$I,Détail!$A:$A,"Hiba LISSAOUI",Détail!$B:$B,$A12,Détail!$C:$C,$B12),"") | H12: =COUNTIFS(Détail!$A:$A,"Imad RMAIDI",Détail!$B:$B,$A12,Détail!$C:$C,$B12,Détail!$E:$E,"<>(à saisir)") | I12: =IFERROR(AVERAGEIFS(Détail!$I:$I,Détail!$A:$A,"Imad RMAIDI",Détail!$B:$B,$A12,Détail!$C:$C,$B12),"") | J12: =COUNTIFS(Détail!$A:$A,"Mohamed HAMDANI",Détail!$B:$B,$A12,Détail!$C:$C,$B12,Détail!$E:$E,"<>(à saisir)") | K12: =IFERROR(AVERAGEIFS(Détail!$I:$I,Détail!$A:$A,"Mohamed HAMDANI",Détail!$B:$B,$A12,Détail!$C:$C,$B12),"") | L12: =COUNTIFS(Détail!$A:$A,"Youssef",Détail!$B:$B,$A12,Détail!$C:$C,$B12,Détail!$E:$E,"<>(à saisir)") | M12: =IFERROR(AVERAGEIFS(Détail!$I:$I,Détail!$A:$A,"Youssef",Détail!$B:$B,$A12,Détail!$C:$C,$B12),"") | N12: =COUNTIFS(Détail!$B:$B,$A12,Détail!$C:$C,$B12,Détail!$E:$E,"<>(à saisir)") | O12: =IFERROR(AVERAGEIFS(Détail!$I:$I,Détail!$B:$B,$A12,Détail!$C:$C,$B12),"")
A13: 2026 | B13: 6 | C13: 02/02/2026 – 08/02/2026 | D13: =COUNTIFS(Détail!$A:$A,"Hafssa BENCHRIF",Détail!$B:$B,$A13,Détail!$C:$C,$B13,Détail!$E:$E,"<>(à saisir)") | E13: =IFERROR(AVERAGEIFS(Détail!$I:$I,Détail!$A:$A,"Hafssa BENCHRIF",Détail!$B:$B,$A13,Détail!$C:$C,$B13),"") | F13: =COUNTIFS(Détail!$A:$A,"Hiba LISSAOUI",Détail!$B:$B,$A13,Détail!$C:$C,$B13,Détail!$E:$E,"<>(à saisir)") | G13: =IFERROR(AVERAGEIFS(Détail!$I:$I,Détail!$A:$A,"Hiba LISSAOUI",Détail!$B:$B,$A13,Détail!$C:$C,$B13),"") | H13: =COUNTIFS(Détail!$A:$A,"Imad RMAIDI",Détail!$B:$B,$A13,Détail!$C:$C,$B13,Détail!$E:$E,"<>(à saisir)") | I13: =IFERROR(AVERAGEIFS(Détail!$I:$I,Détail!$A:$A,"Imad RMAIDI",Détail!$B:$B,$A13,Détail!$C:$C,$B13),"") | J13: =COUNTIFS(Détail!$A:$A,"Mohamed HAMDANI",Détail!$B:$B,$A13,Détail!$C:$C,$B13,Détail!$E:$E,"<>(à saisir)") | K13: =IFERROR(AVERAGEIFS(Détail!$I:$I,Détail!$A:$A,"Mohamed HAMDANI",Détail!$B:$B,$A13,Détail!$C:$C,$B13),"") | L13: =COUNTIFS(Détail!$A:$A,"Youssef",Détail!$B:$B,$A13,Détail!$C:$C,$B13,Détail!$E:$E,"<>(à saisir)") | M13: =IFERROR(AVERAGEIFS(Détail!$I:$I,Détail!$A:$A,"Youssef",Détail!$B:$B,$A13,Détail!$C:$C,$B13),"") | N13: =COUNTIFS(Détail!$B:$B,$A13,Détail!$C:$C,$B13,Détail!$E:$E,"<>(à saisir)") | O13: =IFERROR(AVERAGEIFS(Détail!$I:$I,Détail!$B:$B,$A13,Détail!$C:$C,$B13),"")
A14: 2026 | B14: 7 | C14: 09/02/2026 – 15/02/2026 | D14: =COUNTIFS(Détail!$A:$A,"Hafssa BENCHRIF",Détail!$B:$B,$A14,Détail!$C:$C,$B14,Détail!$E:$E,"<>(à saisir)") | E14: =IFERROR(AVERAGEIFS(Détail!$I:$I,Détail!$A:$A,"Hafssa BENCHRIF",Détail!$B:$B,$A14,Détail!$C:$C,$B14),"") | F14: =COUNTIFS(Détail!$A:$A,"Hiba LISSAOUI",Détail!$B:$B,$A14,Détail!$C:$C,$B14,Détail!$E:$E,"<>(à saisir)") | G14: =IFERROR(AVERAGEIFS(Détail!$I:$I,Détail!$A:$A,"Hiba LISSAOUI",Détail!$B:$B,$A14,Détail!$C:$C,$B14),"") | H14: =COUNTIFS(Détail!$A:$A,"Imad RMAIDI",Détail!$B:$B,$A14,Détail!$C:$C,$B14,Détail!$E:$E,"<>(à saisir)") | I14: =IFERROR(AVERAGEIFS(Détail!$I:$I,Détail!$A:$A,"Imad RMAIDI",Détail!$B:$B,$A14,Détail!$C:$C,$B14),"") | J14: =COUNTIFS(Détail!$A:$A,"Mohamed HAMDANI",Détail!$B:$B,$A14,Détail!$C:$C,$B14,Détail!$E:$E,"<>(à saisir)") | K14: =IFERROR(AVERAGEIFS(Détail!$I:$I,Détail!$A:$A,"Mohamed HAMDANI",Détail!$B:$B,$A14,Détail!$C:$C,$B14),"") | L14: =COUNTIFS(Détail!$A:$A,"Youssef",Détail!$B:$B,$A14,Détail!$C:$C,$B14,Détail!$E:$E,"<>(à saisir)") | M14: =IFERROR(AVERAGEIFS(Détail!$I:$I,Détail!$A:$A,"Youssef",Détail!$B:$B,$A14,Détail!$C:$C,$B14),"") | N14: =COUNTIFS(Détail!$B:$B,$A14,Détail!$C:$C,$B14,Détail!$E:$E,"<>(à saisir)") | O14: =IFERROR(AVERAGEIFS(Détail!$I:$I,Détail!$B:$B,$A14,Détail!$C:$C,$B14),"")
A15: 2026 | B15: 8 | C15: 16/02/2026 – 22/02/2026 | D15: =COUNTIFS(Détail!$A:$A,"Hafssa BENCHRIF",Détail!$B:$B,$A15,Détail!$C:$C,$B15,Détail!$E:$E,"<>(à saisir)") | E15: =IFERROR(AVERAGEIFS(Détail!$I:$I,Détail!$A:$A,"Hafssa BENCHRIF",Détail!$B:$B,$A15,Détail!$C:$C,$B15),"") | F15: =COUNTIFS(Détail!$A:$A,"Hiba LISSAOUI",Détail!$B:$B,$A15,Détail!$C:$C,$B15,Détail!$E:$E,"<>(à saisir)") | G15: =IFERROR(AVERAGEIFS(Détail!$I:$I,Détail!$A:$A,"Hiba LISSAOUI",Détail!$B:$B,$A15,Détail!$C:$C,$B15),"") | H15: =COUNTIFS(Détail!$A:$A,"Imad RMAIDI",Détail!$B:$B,$A15,Détail!$C:$C,$B15,Détail!$E:$E,"<>(à saisir)") | I15: =IFERROR(AVERAGEIFS(Détail!$I:$I,Détail!$A:$A,"Imad RMAIDI",Détail!$B:$B,$A15,Détail!$C:$C,$B15),"") | J15: =COUNTIFS(Détail!$A:$A,"Mohamed HAMDANI",Détail!$B:$B,$A15,Détail!$C:$C,$B15,Détail!$E:$E,"<>(à saisir)") | K15: =IFERROR(AVERAGEIFS(Détail!$I:$I,Détail!$A:$A,"Mohamed HAMDANI",Détail!$B:$B,$A15,Détail!$C:$C,$B15),"") | L15: =COUNTIFS(Détail!$A:$A,"Youssef",Détail!$B:$B,$A15,Détail!$C:$C,$B15,Détail!$E:$E,"<>(à saisir)") | M15: =IFERROR(AVERAGEIFS(Détail!$I:$I,Détail!$A:$A,"Youssef",Détail!$B:$B,$A15,Détail!$C:$C,$B15),"") | N15: =COUNTIFS(Détail!$B:$B,$A15,Détail!$C:$C,$B15,Détail!$E:$E,"<>(à saisir)") | O15: =IFERROR(AVERAGEIFS(Détail!$I:$I,Détail!$B:$B,$A15,Détail!$C:$C,$B15),"")
A16: 2026 | B16: 9 | C16: 23/02/2026 – 01/03/2026 | D16: =COUNTIFS(Détail!$A:$A,"Hafssa BENCHRIF",Détail!$B:$B,$A16,Détail!$C:$C,$B16,Détail!$E:$E,"<>(à saisir)") | E16: =IFERROR(AVERAGEIFS(Détail!$I:$I,Détail!$A:$A,"Hafssa BENCHRIF",Détail!$B:$B,$A16,Détail!$C:$C,$B16),"") | F16: =COUNTIFS(Détail!$A:$A,"Hiba LISSAOUI",Détail!$B:$B,$A16,Détail!$C:$C,$B16,Détail!$E:$E,"<>(à saisir)") | G16: =IFERROR(AVERAGEIFS(Détail!$I:$I,Détail!$A:$A,"Hiba LISSAOUI",Détail!$B:$B,$A16,Détail!$C:$C,$B16),"") | H16: =COUNTIFS(Détail!$A:$A,"Imad RMAIDI",Détail!$B:$B,$A16,Détail!$C:$C,$B16,Détail!$E:$E,"<>(à saisir)") | I16: =IFERROR(AVERAGEIFS(Détail!$I:$I,Détail!$A:$A,"Imad RMAIDI",Détail!$B:$B,$A16,Détail!$C:$C,$B16),"") | J16: =COUNTIFS(Détail!$A:$A,"Mohamed HAMDANI",Détail!$B:$B,$A16,Détail!$C:$C,$B16,Détail!$E:$E,"<>(à saisir)") | K16: =IFERROR(AVERAGEIFS(Détail!$I:$I,Détail!$A:$A,"Mohamed HAMDANI",Détail!$B:$B,$A16,Détail!$C:$C,$B16),"") | L16: =COUNTIFS(Détail!$A:$A,"Youssef",Détail!$B:$B,$A16,Détail!$C:$C,$B16,Détail!$E:$E,"<>(à saisir)") | M16: =IFERROR(AVERAGEIFS(Détail!$I:$I,Détail!$A:$A,"Youssef",Détail!$B:$B,$A16,Détail!$C:$C,$B16),"") | N16: =COUNTIFS(Détail!$B:$B,$A16,Détail!$C:$C,$B16,Détail!$E:$E,"<>(à saisir)") | O16: =IFERROR(AVERAGEIFS(Détail!$I:$I,Détail!$B:$B,$A16,Détail!$C:$C,$B16),"")
A17: 2026 | B17: 10 | C17: 02/03/2026 – 08/03/2026 | D17: =COUNTIFS(Détail!$A:$A,"Hafssa BENCHRIF",Détail!$B:$B,$A17,Détail!$C:$C,$B17,Détail!$E:$E,"<>(à saisir)") | E17: =IFERROR(AVERAGEIFS(Détail!$I:$I,Détail!$A:$A,"Hafssa BENCHRIF",Détail!$B:$B,$A17,Détail!$C:$C,$B17),"") | F17: =COUNTIFS(Détail!$A:$A,"Hiba LISSAOUI",Détail!$B:$B,$A17,Détail!$C:$C,$B17,Détail!$E:$E,"<>(à saisir)") | G17: =IFERROR(AVERAGEIFS(Détail!$I:$I,Détail!$A:$A,"Hiba LISSAOUI",Détail!$B:$B,$A17,Détail!$C:$C,$B17),"") | H17: =COUNTIFS(Détail!$A:$A,"Imad RMAIDI",Détail!$B:$B,$A17,Détail!$C:$C,$B17,Détail!$E:$E,"<>(à saisir)") | I17: =IFERROR(AVERAGEIFS(Détail!$I:$I,Détail!$A:$A,"Imad RMAIDI",Détail!$B:$B,$A17,Détail!$C:$C,$B17),"") | J17: =COUNTIFS(Détail!$A:$A,"Mohamed HAMDANI",Détail!$B:$B,$A17,Détail!$C:$C,$B17,Détail!$E:$E,"<>(à saisir)") | K17: =IFERROR(AVERAGEIFS(Détail!$I:$I,Détail!$A:$A,"Mohamed HAMDANI",Détail!$B:$B,$A17,Détail!$C:$C,$B17),"") | L17: =COUNTIFS(Détail!$A:$A,"Youssef",Détail!$B:$B,$A17,Détail!$C:$C,$B17,Détail!$E:$E,"<>(à saisir)") | M17: =IFERROR(AVERAGEIFS(Détail!$I:$I,Détail!$A:$A,"Youssef",Détail!$B:$B,$A17,Détail!$C:$C,$B17),"") | N17: =COUNTIFS(Détail!$B:$B,$A17,Détail!$C:$C,$B17,Détail!$E:$E,"<>(à saisir)") | O17: =IFERROR(AVERAGEIFS(Détail!$I:$I,Détail!$B:$B,$A17,Détail!$C:$C,$B17),"")
... A51: 2026 | B51: 44 | C51: 26/10/2026 – 01/11/2026 | D51: =COUNTIFS(Détail!$A:$A,"Hafssa BENCHRIF",Détail!$B:$B,$A51,Détail!$C:$C,$B51,Détail!$E:$E,"<>(à saisir)") | E51: =IFERROR(AVERAGEIFS(Détail!$I:$I,Détail!$A:$A,"Hafssa BENCHRIF",Détail!$B:$B,$A51,Détail!$C:$C,$B51),"") | F51: =COUNTIFS(Détail!$A:$A,"Hiba LISSAOUI",Détail!$B:$B,$A51,Détail!$C:$C,$B51,Détail!$E:$E,"<>(à saisir)") | G51: =IFERROR(AVERAGEIFS(Détail!$I:$I,Détail!$A:$A,"Hiba LISSAOUI",Détail!$B:$B,$A51,Détail!$C:$C,$B51),"") | H51: =COUNTIFS(Détail!$A:$A,"Imad RMAIDI",Détail!$B:$B,$A51,Détail!$C:$C,$B51,Détail!$E:$E,"<>(à saisir)") | I51: =IFERROR(AVERAGEIFS(Détail!$I:$I,Détail!$A:$A,"Imad RMAIDI",Détail!$B:$B,$A51,Détail!$C:$C,$B51),"") | J51: =COUNTIFS(Détail!$A:$A,"Mohamed HAMDANI",Détail!$B:$B,$A51,Détail!$C:$C,$B51,Détail!$E:$E,"<>(à saisir)") | K51: =IFERROR(AVERAGEIFS(Détail!$I:$I,Détail!$A:$A,"Mohamed HAMDANI",Détail!$B:$B,$A51,Détail!$C:$C,$B51),"") | L51: =COUNTIFS(Détail!$A:$A,"Youssef",Détail!$B:$B,$A51,Détail!$C:$C,$B51,Détail!$E:$E,"<>(à saisir)") | M51: =IFERROR(AVERAGEIFS(Détail!$I:$I,Détail!$A:$A,"Youssef",Détail!$B:$B,$A51,Détail!$C:$C,$B51),"") | N51: =COUNTIFS(Détail!$B:$B,$A51,Détail!$C:$C,$B51,Détail!$E:$E,"<>(à saisir)") | O51: =IFERROR(AVERAGEIFS(Détail!$I:$I,Détail!$B:$B,$A51,Détail!$C:$C,$B51),"")
A52: Total / moyenne | D52: =SUM(D6:D51) | E52: =IFERROR(AVERAGEIFS(Détail!$I:$I,Détail!$A:$A,"Hafssa BENCHRIF"),"") | F52: =SUM(F6:F51) | G52: =IFERROR(AVERAGEIFS(Détail!$I:$I,Détail!$A:$A,"Hiba LISSAOUI"),"") | H52: =SUM(H6:H51) | I52: =IFERROR(AVERAGEIFS(Détail!$I:$I,Détail!$A:$A,"Imad RMAIDI"),"") | J52: =SUM(J6:J51) | K52: =IFERROR(AVERAGEIFS(Détail!$I:$I,Détail!$A:$A,"Mohamed HAMDANI"),"") | L52: =SUM(L6:L51) | M52: =IFERROR(AVERAGEIFS(Détail!$I:$I,Détail!$A:$A,"Youssef"),"") | N52: =SUM(N6:N51) | O52: =IFERROR(AVERAGE(Détail!$I:$I),"")

Sheet Par collaborateur
A1: Bilan par collaborateur
A3: Collaborateur | B3: Documents traités | C3: Documents évalués | D3: Semaines actives | E3: Note moyenne /100 | F3: Note min. | G3: Documents à 100 % | H3: Documents < 100 % | I3: Documents < 85 % | J3: Rapports manquants | K3: Critères non conformes | L3: Notes à saisir (jaune)
A4: Hafssa BENCHRIF | B4: =COUNTIFS(Détail!$A:$A,"Hafssa BENCHRIF",Détail!$E:$E,"<>(à saisir)") | C4: =COUNTIFS(Détail!$A:$A,"Hafssa BENCHRIF",Détail!$I:$I,">=0") | D4: =SUMPRODUCT((Détail!$A$2:$A$142="Hafssa BENCHRIF")*(Détail!$E$2:$E$142<>"(à saisir)")/COUNTIFS(Détail!$A$2:$A$142,Détail!$A$2:$A$142,Détail!$D$2:$D$142,Détail!$D$2:$D$142)) | E4: =IFERROR(AVERAGEIFS(Détail!$I:$I,Détail!$A:$A,"Hafssa BENCHRIF"),"") | F4: =_xlfn.MINIFS(Détail!$I$2:$I$142,Détail!$A$2:$A$142,"Hafssa BENCHRIF") | G4: =COUNTIFS(Détail!$A:$A,"Hafssa BENCHRIF",Détail!$I:$I,">=99.95") | H4: =COUNTIFS(Détail!$A:$A,"Hafssa BENCHRIF",Détail!$I:$I,"<99.95") | I4: =COUNTIFS(Détail!$A:$A,"Hafssa BENCHRIF",Détail!$I:$I,"<85") | J4: =B4-C4 | K4: =SUMIFS(Détail!$L:$L,Détail!$A:$A,"Hafssa BENCHRIF") | L4: =COUNTIFS(Détail!$A:$A,"Hafssa BENCHRIF",Détail!$J:$J,"À saisir")
A5: Hiba LISSAOUI | B5: =COUNTIFS(Détail!$A:$A,"Hiba LISSAOUI",Détail!$E:$E,"<>(à saisir)") | C5: =COUNTIFS(Détail!$A:$A,"Hiba LISSAOUI",Détail!$I:$I,">=0") | D5: =SUMPRODUCT((Détail!$A$2:$A$142="Hiba LISSAOUI")*(Détail!$E$2:$E$142<>"(à saisir)")/COUNTIFS(Détail!$A$2:$A$142,Détail!$A$2:$A$142,Détail!$D$2:$D$142,Détail!$D$2:$D$142)) | E5: =IFERROR(AVERAGEIFS(Détail!$I:$I,Détail!$A:$A,"Hiba LISSAOUI"),"") | F5: =_xlfn.MINIFS(Détail!$I$2:$I$142,Détail!$A$2:$A$142,"Hiba LISSAOUI") | G5: =COUNTIFS(Détail!$A:$A,"Hiba LISSAOUI",Détail!$I:$I,">=99.95") | H5: =COUNTIFS(Détail!$A:$A,"Hiba LISSAOUI",Détail!$I:$I,"<99.95") | I5: =COUNTIFS(Détail!$A:$A,"Hiba LISSAOUI",Détail!$I:$I,"<85") | J5: =B5-C5 | K5: =SUMIFS(Détail!$L:$L,Détail!$A:$A,"Hiba LISSAOUI") | L5: =COUNTIFS(Détail!$A:$A,"Hiba LISSAOUI",Détail!$J:$J,"À saisir")
A6: Imad RMAIDI | B6: =COUNTIFS(Détail!$A:$A,"Imad RMAIDI",Détail!$E:$E,"<>(à saisir)") | C6: =COUNTIFS(Détail!$A:$A,"Imad RMAIDI",Détail!$I:$I,">=0") | D6: =SUMPRODUCT((Détail!$A$2:$A$142="Imad RMAIDI")*(Détail!$E$2:$E$142<>"(à saisir)")/COUNTIFS(Détail!$A$2:$A$142,Détail!$A$2:$A$142,Détail!$D$2:$D$142,Détail!$D$2:$D$142)) | E6: =IFERROR(AVERAGEIFS(Détail!$I:$I,Détail!$A:$A,"Imad RMAIDI"),"") | F6: =_xlfn.MINIFS(Détail!$I$2:$I$142,Détail!$A$2:$A$142,"Imad RMAIDI") | G6: =COUNTIFS(Détail!$A:$A,"Imad RMAIDI",Détail!$I:$I,">=99.95") | H6: =COUNTIFS(Détail!$A:$A,"Imad RMAIDI",Détail!$I:$I,"<99.95") | I6: =COUNTIFS(Détail!$A:$A,"Imad RMAIDI",Détail!$I:$I,"<85") | J6: =B6-C6 | K6: =SUMIFS(Détail!$L:$L,Détail!$A:$A,"Imad RMAIDI") | L6: =COUNTIFS(Détail!$A:$A,"Imad RMAIDI",Détail!$J:$J,"À saisir")
A7: Mohamed HAMDANI | B7: =COUNTIFS(Détail!$A:$A,"Mohamed HAMDANI",Détail!$E:$E,"<>(à saisir)") | C7: =COUNTIFS(Détail!$A:$A,"Mohamed HAMDANI",Détail!$I:$I,">=0") | D7: =SUMPRODUCT((Détail!$A$2:$A$142="Mohamed HAMDANI")*(Détail!$E$2:$E$142<>"(à saisir)")/COUNTIFS(Détail!$A$2:$A$142,Détail!$A$2:$A$142,Détail!$D$2:$D$142,Détail!$D$2:$D$142)) | E7: =IFERROR(AVERAGEIFS(Détail!$I:$I,Détail!$A:$A,"Mohamed HAMDANI"),"") | F7: =_xlfn.MINIFS(Détail!$I$2:$I$142,Détail!$A$2:$A$142,"Mohamed HAMDANI") | G7: =COUNTIFS(Détail!$A:$A,"Mohamed HAMDANI",Détail!$I:$I,">=99.95") | H7: =COUNTIFS(Détail!$A:$A,"Mohamed HAMDANI",Détail!$I:$I,"<99.95") | I7: =COUNTIFS(Détail!$A:$A,"Mohamed HAMDANI",Détail!$I:$I,"<85") | J7: =B7-C7 | K7: =SUMIFS(Détail!$L:$L,Détail!$A:$A,"Mohamed HAMDANI") | L7: =COUNTIFS(Détail!$A:$A,"Mohamed HAMDANI",Détail!$J:$J,"À saisir")
A8: Youssef | B8: =COUNTIFS(Détail!$A:$A,"Youssef",Détail!$E:$E,"<>(à saisir)") | C8: =COUNTIFS(Détail!$A:$A,"Youssef",Détail!$I:$I,">=0") | D8: =SUMPRODUCT((Détail!$A$2:$A$142="Youssef")*(Détail!$E$2:$E$142<>"(à saisir)")/COUNTIFS(Détail!$A$2:$A$142,Détail!$A$2:$A$142,Détail!$D$2:$D$142,Détail!$D$2:$D$142)) | E8: =IFERROR(AVERAGEIFS(Détail!$I:$I,Détail!$A:$A,"Youssef"),"") | F8: =_xlfn.MINIFS(Détail!$I$2:$I$142,Détail!$A$2:$A$142,"Youssef") | G8: =COUNTIFS(Détail!$A:$A,"Youssef",Détail!$I:$I,">=99.95") | H8: =COUNTIFS(Détail!$A:$A,"Youssef",Détail!$I:$I,"<99.95") | I8: =COUNTIFS(Détail!$A:$A,"Youssef",Détail!$I:$I,"<85") | J8: =B8-C8 | K8: =SUMIFS(Détail!$L:$L,Détail!$A:$A,"Youssef") | L8: =COUNTIFS(Détail!$A:$A,"Youssef",Détail!$J:$J,"À saisir")
A9: Équipe | B9: =SUM(B4:B8) | C9: =SUM(C4:C8) | D9: =SUM(D4:D8) | E9: =IFERROR(AVERAGE(Détail!$I:$I),"") | F9: =MIN(F4:F8) | G9: =SUM(G4:G8) | H9: =SUM(H4:H8) | I9: =SUM(I4:I8) | J9: =SUM(J4:J8) | K9: =SUM(K4:K8) | L9: =SUM(L4:L8)
A11: Seuil de conformité retenu : 85 % (identique aux rapports RAPDF). « Semaines actives » = semaines avec au moins un document.

Sheet Détail
A1: Collaborateur | B1: Année | C1: Semaine | D1: Clé semaine | E1: Document | F1: Type | G1: Date d'évaluation | H1: Source | I1: Note /100 | J1: Statut | K1: Critères conformes | L1: Critères non conformes | M1: Critères non applicables | N1: Détail des critères non conformes | O1: Action corrective | P1: Jours planifiés | Q1: Présents | R1: Absents | S1: Non renseignés | T1: Congés | U1: Jours fériés | V1: Nb retards | W1: Retards (min) | X1: Heures planifiées | Y1: Heures adhérées | Z1: Taux d’assiduité | AA1: Adhérence heures
A2: Hafssa BENCHRIF | B2: 2025 | C2: 51 | D2: =B2&"-S"&TEXT(C2,"00") | E2: CG0570v02 0525 | F2: word | H2: Grille | I2: 100 | J2: =IF(I2="","Rapport manquant",IF(I2>=85,"CONFORME (≥85%)","NON CONFORME (<85%)")) | K2: 10 | L2: 0 | M2: 36 | P2: 0 | Q2: 0 | R2: 0 | S2: 0 | T2: 0 | U2: 0 | V2: 0 | W2: 0 | X2: 0 | Y2: 0
A3: Hafssa BENCHRIF | B3: 2025 | C3: 51 | D3: =B3&"-S"&TEXT(C3,"00") | E3: CM0409v04 1214 LIVRET PUNCH | F3: word | H3: Grille | I3: 100 | J3: =IF(I3="","Rapport manquant",IF(I3>=85,"CONFORME (≥85%)","NON CONFORME (<85%)")) | K3: 8 | L3: 0 | M3: 38 | P3: 0 | Q3: 0 | R3: 0 | S3: 0 | T3: 0 | U3: 0 | V3: 0 | W3: 0 | X3: 0 | Y3: 0
A4: Hiba LISSAOUI | B4: 2025 | C4: 51 | D4: =B4&"-S"&TEXT(C4,"00") | E4: CG.05.78v02 1024 CG BAD EI CM CIC | F4: word | H4: Grille | I4: 96.7 | J4: =IF(I4="","À saisir",IF(I4>=85,"CONFORME (≥85%)","NON CONFORME (<85%)")) | K4: 9 | L4: 1 | M4: 36 | N4: 5.2 – Chaque contenu présenté sous forme de liste utilise-t-il un style de liste ? | O4: Debrief de l’agent pour le sensibiliser à l’importance d’être vigilant sur le traitement, puis exercice pratique avec l’ensemble de l’équipe. | P4: 0 | Q4: 0 | R4: 0 | S4: 0 | T4: 0 | U4: 0 | V4: 0 | W4: 0 | X4: 0 | Y4: 0
A5: Hiba LISSAOUI | B5: 2025 | C5: 51 | D5: =B5&"-S"&TEXT(C5,"00") | E5: CG0566 0725 CM | F5: word | H5: Grille | I5: 100 | J5: =IF(I5="","À saisir",IF(I5>=85,"CONFORME (≥85%)","NON CONFORME (<85%)")) | K5: 10 | L5: 0 | M5: 36 | P5: 0 | Q5: 0 | R5: 0 | S5: 0 | T5: 0 | U5: 0 | V5: 0 | W5: 0 | X5: 0 | Y5: 0
A6: Imad RMAIDI | B6: 2025 | C6: 51 | D6: =B6&"-S"&TEXT(C6,"00") | E6: CG0443v02 1214 LIVRET BIENVENUE + | F6: word | H6: Grille | I6: 100 | J6: =IF(I6="","À saisir",IF(I6>=85,"CONFORME (≥85%)","NON CONFORME (<85%)")) | K6: 9 | L6: 0 | M6: 37 | P6: 0 | Q6: 0 | R6: 0 | S6: 0 | T6: 0 | U6: 0 | V6: 0 | W6: 0 | X6: 0 | Y6: 0
A7: Imad RMAIDI | B7: 2025 | C7: 51 | D7: =B7&"-S"&TEXT(C7,"00") | E7: CM0310v03 1122 livret bleu Prem's | F7: word | H7: Grille | I7: 100 | J7: =IF(I7="","À saisir",IF(I7>=85,"CONFORME (≥85%)","NON CONFORME (<85%)")) | K7: 12 | L7: 0 | M7: 34 | P7: 0 | Q7: 0 | R7: 0 | S7: 0 | T7: 0 | U7: 0 | V7: 0 | W7: 0 | X7: 0 | Y7: 0
A8: Mohamed HAMDANI | B8: 2025 | C8: 51 | D8: =B8&"-S"&TEXT(C8,"00") | E8: CI0396v03 1018 CG carte de retrait DE | F8: word | H8: Grille | I8: 100 | J8: =IF(I8="","À saisir",IF(I8>=85,"CONFORME (≥85%)","NON CONFORME (<85%)")) | K8: 11 | L8: 0 | M8: 35 | P8: 0 | Q8: 0 | R8: 0 | S8: 0 | T8: 0 | U8: 0 | V8: 0 | W8: 0 | X8: 0 | Y8: 0
A9: Mohamed HAMDANI | B9: 2025 | C9: 51 | D9: =B9&"-S"&TEXT(C9,"00") | E9: CM0575v01 0324 Carte achat public | F9: word | H9: Grille | I9: 93.3 | J9: =IF(I9="","À saisir",IF(I9>=85,"CONFORME (≥85%)","NON CONFORME (<85%)")) | K9: 12 | L9: 2 | M9: 32 | N9: 5.1 – L’information est-elle structurée par l’utilisation appropriée de titres ? 5.2 – Chaque contenu présenté sous forme de liste utilise-t-il un style de liste ? | O9: Debrief de l’agent pour le sensibiliser à l’importance d’être vigilant sur le traitement, puis exercice pratique avec l’ensemble de l’équipe. | P9: 0 | Q9: 0 | R9: 0 | S9: 0 | T9: 0 | U9: 0 | V9: 0 | W9: 0 | X9: 0 | Y9: 0
A10: Hafssa BENCHRIF | B10: 2025 | C10: 52 | D10: =B10&"-S"&TEXT(C10,"00") | E10: CG0563v01 0123 CG Services de Dépôt | F10: word | H10: Grille | I10: 100 | J10: =IF(I10="","Rapport manquant",IF(I10>=85,"CONFORME (≥85%)","NON CONFORME (<85%)")) | K10: 9 | L10: 0 | M10: 37 | P10: 4 | Q10: 4 | R10: 0 | S10: 0 | T10: 0 | U10: 0 | V10: 0 | W10: 0 | X10: 1.4583333 | Y10: 1.4583333 | Z10: 1 | AA10: 1
A11: Hafssa BENCHRIF | B11: 2025 | C11: 52 | D11: =B11&"-S"&TEXT(C11,"00") | E11: CG0706 1219 | F11: word | H11: Grille | I11: 100 | J11: =IF(I11="","Rapport manquant",IF(I11>=85,"CONFORME (≥85%)","NON CONFORME (<85%)")) | K11: 13 | L11: 0 | M11: 33 | P11: 4 | Q11: 4 | R11: 0 | S11: 0 | T11: 0 | U11: 0 | V11: 0 | W11: 0 | X11: 1.4583333 | Y11: 1.4583333 | Z11: 1 | AA11: 1
A12: Hiba LISSAOUI | B12: 2025 | C12: 52 | D12: =B12&"-S"&TEXT(C12,"00") | E12: CG0704 1120 | F12: word | H12: Grille | I12: 96.7 | J12: =IF(I12="","À saisir",IF(I12>=85,"CONFORME (≥85%)","NON CONFORME (<85%)")) | K12: 14 | L12: 1 | M12: 31 | N12: 6.3 – Chaque lien signalé uniquement par la couleur et dont la nature n’est pas évidente est-il visible, par rapport au texte environnant ? | O12: Debrief de l’agent pour le sensibiliser à l’importance d’être vigilant sur le traitement, puis exercice pratique avec l’ensemble de l’équipe. | P12: 4 | Q12: 4 | R12: 0 | S12: 0 | T12: 0 | U12: 0 | V12: 0 | W12: 0 | X12: 1.4583333 | Y12: 1.4583333 | Z12: 1 | AA12: 1
A13: Hiba LISSAOUI | B13: 2025 | C13: 52 | D13: =B13&"-S"&TEXT(C13,"00") | E13: GR8884v11 0122 caut PP EPS | F13: word | H13: Grille | I13: 100 | J13: =IF(I13="","À saisir",IF(I13>=85,"CONFORME (≥85%)","NON CONFORME (<85%)")) | K13: 14 | L13: 0 | M13: 32 | P13: 4 | Q13: 4 | R13: 0 | S13: 0 | T13: 0 | U13: 0 | V13: 0 | W13: 0 | X13: 1.4583333 | Y13: 1.4583333 | Z13: 1 | AA13: 1
A14: Imad RMAIDI | B14: 2025 | C14: 52 | D14: =B14&"-S"&TEXT(C14,"00") | E14: CG0403v02 0314 CG Livret bienvenue DE | F14: word | H14: Grille | I14: 100 | J14: =IF(I14="","À saisir",IF(I14>=85,"CONFORME (≥85%)","NON CONFORME (<85%)")) | K14: 10 | L14: 0 | M14: 36 | P14: 4 | Q14: 4 | R14: 0 | S14: 0 | T14: 0 | U14: 0 | V14: 0 | W14: 0 | X14: 1.4583333 | Y14: 1.4583333 | Z14: 1 | AA14: 1
A15: Imad RMAIDI | B15: 2025 | C15: 52 | D15: =B15&"-S"&TEXT(C15,"00") | E15: CG0523v01 0616 Livret Crescendo UK | F15: word | H15: Grille | I15: 100 | J15: =IF(I15="","À saisir",IF(I15>=85,"CONFORME (≥85%)","NON CONFORME (<85%)")) | K15: 10 | L15: 0 | M15: 36 | P15: 4 | Q15: 4 | R15: 0 | S15: 0 | T15: 0 | U15: 0 | V15: 0 | W15: 0 | X15: 1.4583333 | Y15: 1.4583333 | Z15: 1 | AA15: 1
A16: Mohamed HAMDANI | B16: 2025 | C16: 52 | D16: =B16&"-S"&TEXT(C16,"00") | E16: CG0309v01 0710 carte authen bancaire FR | F16: word | H16: Grille | I16: 100 | J16: =IF(I16="","À saisir",IF(I16>=85,"CONFORME (≥85%)","NON CONFORME (<85%)")) | K16: 9 | L16: 0 | M16: 37 | P16: 4 | Q16: 4 | R16: 0 | S16: 0 | T16: 0 | U16: 0 | V16: 0 | W16: 0 | X16: 1.4583333 | Y16: 1.4583333 | Z16: 1 | AA16: 1
A17: Mohamed HAMDANI | B17: 2025 | C17: 52 | D17: =B17&"-S"&TEXT(C17,"00") | E17: CG0309v01 0710 carte authen bancaire UK | F17: word | H17: Grille | I17: 100 | J17: =IF(I17="","À saisir",IF(I17>=85,"CONFORME (≥85%)","NON CONFORME (<85%)")) | K17: 9 | L17: 0 | M17: 37 | P17: 4 | Q17: 4 | R17: 0 | S17: 0 | T17: 0 | U17: 0 | V17: 0 | W17: 0 | X17: 1.4583333 | Y17: 1.4583333 | Z17: 1 | AA17: 1
A18: Hafssa BENCHRIF | B18: 2026 | C18: 1 | D18: =B18&"-S"&TEXT(C18,"00") | E18: GR8860v08 0122 nant ass vie ss contre ass | F18: word | H18: Grille | I18: 100 | J18: =IF(I18="","Rapport manquant",IF(I18>=85,"CONFORME (≥85%)","NON CONFORME (<85%)")) | K18: 14 | L18: 0 | M18: 32 | P18: 4 | Q18: 4 | R18: 0 | S18: 0 | T18: 0 | U18: 1 | V18: 0 | W18: 0 | X18: 1.4583333 | Y18: 1.4583333 | Z18: 1 | AA18: 1
A19: Hiba LISSAOUI | B19: 2026 | C19: 1 | D19: =B19&"-S"&TEXT(C19,"00") | E19: CG0212v02 0214 conv information conseil | F19: word | H19: Grille | I19: 100 | J19: =IF(I19="","À saisir",IF(I19>=85,"CONFORME (≥85%)","NON CONFORME (<85%)")) | K19: 10 | L19: 0 | M19: 36 | P19: 4 | Q19: 4 | R19: 0 | S19: 0 | T19: 0 | U19: 1 | V19: 0 | W19: 0 | X19: 1.4583333 | Y19: 1.4583333 | Z19: 1 | AA19: 1
A20: Imad RMAIDI | B20: 2026 | C20: 1 | D20: =B20&"-S"&TEXT(C20,"00") | E20: CG0312 0725 | F20: word | H20: Grille | I20: 100 | J20: =IF(I20="","À saisir",IF(I20>=85,"CONFORME (≥85%)","NON CONFORME (<85%)")) | K20: 10 | L20: 0 | M20: 36 | P20: 4 | Q20: 4 | R20: 0 | S20: 0 | T20: 0 | U20: 1 | V20: 0 | W20: 0 | X20: 1.4583333 | Y20: 1.4583333 | Z20: 1 | AA20: 1
A21: Mohamed HAMDANI | B21: 2026 | C21: 1 | D21: =B21&"-S"&TEXT(C21,"00") | E21: CV0508v03 0922 TCN | F21: word | H21: Grille | I21: 100 | J21: =IF(I21="","À saisir",IF(I21>=85,"CONFORME (≥85%)","NON CONFORME (<85%)")) | K21: 9 | L21: 0 | M21: 37 | P21: 4 | Q21: 4 | R21: 0 | S21: 0 | T21: 0 | U21: 1 | V21: 0 | W21: 0 | X21: 1.4583333 | Y21: 1.4583333 | Z21: 1 | AA21: 1
A22: Hafssa BENCHRIF | B22: 2026 | C22: 2 | D22: =B22&"-S"&TEXT(C22,"00") | E22: CG0309v01 0710 carte authen bancaire DE | F22: word | H22: Grille | I22: 100 | J22: =IF(I22="","Rapport manquant",IF(I22>=85,"CONFORME (≥85%)","NON CONFORME (<85%)")) | K22: 9 | L22: 0 | M22: 37 | P22: 4 | Q22: 4 | R22: 0 | S22: 0 | T22: 1 | U22: 0 | V22: 1 | W22: 5 | X22: 1.5 | Y22: 1.5 | Z22: 1 | AA22: 1
A23: Hiba LISSAOUI | B23: 2026 | C23: 2 | D23: =B23&"-S"&TEXT(C23,"00") | E23: GR8903v04 1021 délég ttle capitalisation | F23: word | H23: Grille | I23: 100 | J23: =IF(I23="","À saisir",IF(I23>=85,"CONFORME (≥85%)","NON CONFORME (<85%)")) | K23: 16 | L23: 0 | M23: 30 | P23: 5 | Q23: 5 | R23: 0 | S23: 0 | T23: 0 | U23: 0 | V23: 0 | W23: 0 | X23: 1.8333333 | Y23: 1.8333333 | Z23: 1 | AA23: 1
A24: Imad RMAIDI | B24: 2026 | C24: 2 | D24: =B24&"-S"&TEXT(C24,"00") | E24: GR8865v11 0123 gage auto | F24: word | H24: Grille | I24: 100 | J24: =IF(I24="","À saisir",IF(I24>=85,"CONFORME (≥85%)","NON CONFORME (<85%)")) | K24: 17 | L24: 0 | M24: 29 | P24: 5 | Q24: 5 | R24: 0 | S24: 0 | T24: 0 | U24: 0 | V24: 0 | W24: 0 | X24: 1.8333333 | Y24: 1.8333333 | Z24: 1 | AA24: 1
A25: Mohamed HAMDANI | B25: 2026 | C25: 2 | D25: =B25&"-S"&TEXT(C25,"00") | E25: GR8875v09 0122 nant cpte bancaire | F25: word | H25: Grille | I25: 100 | J25: =IF(I25="","À saisir",IF(I25>=85,"CONFORME (≥85%)","NON CONFORME (<85%)")) | K25: 17 | L25: 0 | M25: 29 | P25: 5 | Q25: 5 | R25: 0 | S25: 0 | T25: 0 | U25: 0 | V25: 0 | W25: 0 | X25: 1.8333333 | Y25: 1.8333333 | Z25: 1 | AA25: 1
A26: Hafssa BENCHRIF | B26: 2026 | C26: 3 | D26: =B26&"-S"&TEXT(C26,"00") | E26: GR8830v05 0221 prom de gage ou nant | F26: word | H26: Grille | I26: 100 | J26: =IF(I26="","Rapport manquant",IF(I26>=85,"CONFORME (≥85%)","NON CONFORME (<85%)")) | K26: 14 | L26: 0 | M26: 32 | P26: 5 | Q26: 5 | R26: 0 | S26: 0 | T26: 0 | U26: 0 | V26: 0 | W26: 0 | X26: 1.8333333 | Y26: 1.8333333 | Z26: 1 | AA26: 1
A27: Hiba LISSAOUI | B27: 2026 | C27: 3 | D27: =B27&"-S"&TEXT(C27,"00") | E27: CG0103v17 0323 MCD | F27: word | H27: Grille | I27: 100 | J27: =IF(I27="","À saisir",IF(I27>=85,"CONFORME (≥85%)","NON CONFORME (<85%)")) | K27: 10 | L27: 0 | M27: 36 | P27: 5 | Q27: 5 | R27: 0 | S27: 0 | T27: 0 | U27: 0 | V27: 1 | W27: 83 | X27: 1.8333333 | Y27: 1.8333333 | Z27: 1 | AA27: 1
A28: Imad RMAIDI | B28: 2026 | C28: 3 | D28: =B28&"-S"&TEXT(C28,"00") | E28: CI0433v06 0312 Stage prévention | F28: word | H28: Grille | I28: 100 | J28: =IF(I28="","À saisir",IF(I28>=85,"CONFORME (≥85%)","NON CONFORME (<85%)")) | K28: 17 | L28: 0 | M28: 29 | P28: 5 | Q28: 5 | R28: 0 | S28: 0 | T28: 0 | U28: 0 | V28: 0 | W28: 0 | X28: 1.8333333 | Y28: 1.8333333 | Z28: 1 | AA28: 1
A29: Mohamed HAMDANI | B29: 2026 | C29: 3 | D29: =B29&"-S"&TEXT(C29,"00") | E29: GR8866v04 0123 bord gage auto | F29: word | H29: Grille | I29: 100 | J29: =IF(I29="","À saisir",IF(I29>=85,"CONFORME (≥85%)","NON CONFORME (<85%)")) | K29: 15 | L29: 0 | M29: 31 | P29: 5 | Q29: 5 | R29: 0 | S29: 0 | T29: 0 | U29: 0 | V29: 0 | W29: 0 | X29: 1.8333333 | Y29: 1.8333333 | Z29: 1 | AA29: 1
A30: Hafssa BENCHRIF | B30: 2026 | C30: 4 | D30: =B30&"-S"&TEXT(C30,"00") | E30: GR8847v03 0122 nant CTF conv | F30: word | H30: Grille | I30: 100 | J30: =IF(I30="","Rapport manquant",IF(I30>=85,"CONFORME (≥85%)","NON CONFORME (<85%)")) | K30: 15 | L30: 0 | M30: 31 | P30: 3 | Q30: 2 | R30: 1 | S30: 0 | T30: 0 | U30: 0 | V30: 0 | W30: 0 | X30: 1.0833333 | Y30: 0.70833333 | Z30: 0.66666667 | AA30: 0.65384615
A31: Hiba LISSAOUI | B31: 2026 | C31: 4 | D31: =B31&"-S"&TEXT(C31,"00") | E31: GR8845v11 0122 nant CTF | F31: word | H31: Grille | I31: 98 | J31: =IF(I31="","À saisir",IF(I31>=85,"CONFORME (≥85%)","NON CONFORME (<85%)")) | K31: 16 | L31: 1 | M31: 29 | N31: 3.4 – Pour chaque tableau de présentation, le contenu linéarisé reste-t-il compréhensible ? | O31: Debrief de l’agent pour le sensibiliser à l’importance d’être vigilant sur le traitement, puis exercice pratique avec l’ensemble de l’équipe. | P31: 3 | Q31: 3 | R31: 0 | S31: 0 | T31: 0 | U31: 0 | V31: 0 | W31: 0 | X31: 1.0833333 | Y31: 1.0833333 | Z31: 1 | AA31: 1
A32: Imad RMAIDI | B32: 2026 | C32: 4 | D32: =B32&"-S"&TEXT(C32,"00") | E32: CM0459v03 1015 CG Tonic Privilege DE | F32: word | H32: Grille | I32: 100 | J32: =IF(I32="","À saisir",IF(I32>=85,"CONFORME (≥85%)","NON CONFORME (<85%)")) | K32: 17 | L32: 0 | M32: 29 | P32: 3 | Q32: 3 | R32: 0 | S32: 0 | T32: 0 | U32: 0 | V32: 0 | W32: 0 | X32: 1.0833333 | Y32: 1.0833333 | Z32: 1 | AA32: 1
A33: Mohamed HAMDANI | B33: 2026 | C33: 4 | D33: =B33&"-S"&TEXT(C33,"00") | E33: CI0464v07 1122 CG livret A Prem_s DE | F33: word | H33: Grille | I33: 100 | J33: =IF(I33="","À saisir",IF(I33>=85,"CONFORME (≥85%)","NON CONFORME (<85%)")) | K33: 10 | L33: 0 | M33: 36 | P33: 3 | Q33: 3 | R33: 0 | S33: 0 | T33: 0 | U33: 0 | V33: 1 | W33: 12 | X33: 1.0833333 | Y33: 1.0833333 | Z33: 1 | AA33: 1
A34: Hafssa BENCHRIF | B34: 2026 | C34: 5 | D34: =B34&"-S"&TEXT(C34,"00") | E34: CG0552v01 0620 AAD | F34: word | H34: Grille | I34: 100 | J34: =IF(I34="","Rapport manquant",IF(I34>=85,"CONFORME (≥85%)","NON CONFORME (<85%)")) | K34: 10 | L34: 0 | M34: 36 | P34: 5 | Q34: 5 | R34: 0 | S34: 0 | T34: 0 | U34: 0 | V34: 0 | W34: 0 | X34: 1.8333333 | Y34: 1.8333333 | Z34: 1 | AA34: 1
A35: Hafssa BENCHRIF | B35: 2026 | C35: 8 | D35: =B35&"-S"&TEXT(C35,"00") | E35: COL_9902030098_011000733309323 | F35: pdf | G35: 46073 | H35: RAPDF | I35: 100 | J35: =IF(I35="","Rapport manquant",IF(I35>=85,"CONFORME (≥85%)","NON CONFORME (<85%)")) | K35: 15 | L35: 0 | M35: 31 | P35: 0 | Q35: 0 | R35: 0 | S35: 0 | T35: 0 | U35: 0 | V35: 0 | W35: 0 | X35: 0 | Y35: 0
A36: Hiba LISSAOUI | B36: 2026 | C36: 8 | D36: =B36&"-S"&TEXT(C36,"00") | E36: EMP_9902030152_011000758125238 | F36: pdf | G36: 46073 | H36: RAPDF | I36: 87.5 | J36: =IF(I36="","À saisir",IF(I36>=85,"CONFORME (≥85%)","NON CONFORME (<85%)")) | K36: 14 | L36: 2 | M36: 30 | N36: 3.1 – Chaque tableau de données complexe a-t-il une alternative ? (le tableau a une alternative "voir texte en bas") 3.2 – Pour chaque tableau de données complexe ayant une alternative, cette alternative est-elle pertinente ? (le texte sous le tableau) | O36: Debrief de l’agent pour le sensibiliser à l’importance d’être vigilant sur le traitement, puis exercice pratique avec l’ensemble de l’équipe. | P36: 0 | Q36: 0 | R36: 0 | S36: 0 | T36: 0 | U36: 0 | V36: 0 | W36: 0 | X36: 0 | Y36: 0
A37: Imad RMAIDI | B37: 2026 | C37: 8 | D37: =B37&"-S"&TEXT(C37,"00") | E37: SAN_9902030040_011000804912506 | F37: pdf | G37: 46073 | H37: RAPDF | I37: 100 | J37: =IF(I37="","À saisir",IF(I37>=85,"CONFORME (≥85%)","NON CONFORME (<85%)")) | K37: 12 | L37: 0 | M37: 28 | P37: 0 | Q37: 0 | R37: 0 | S37: 0 | T37: 0 | U37: 0 | V37: 0 | W37: 0 | X37: 0 | Y37: 0
A38: Mohamed HAMDANI | B38: 2026 | C38: 8 | D38: =B38&"-S"&TEXT(C38,"00") | E38: SAN_9902030040_011000804912412 | F38: pdf | G38: 46073 | H38: RAPDF | I38: 100 | J38: =IF(I38="","À saisir",IF(I38>=85,"CONFORME (≥85%)","NON CONFORME (<85%)")) | K38: 12 | L38: 0 | M38: 34 | P38: 0 | Q38: 0 | R38: 0 | S38: 0 | T38: 0 | U38: 0 | V38: 0 | W38: 0 | X38: 0 | Y38: 0
A39: Hafssa BENCHRIF | B39: 2026 | C39: 9 | D39: =B39&"-S"&TEXT(C39,"00") | E39: COL_9902030098_011000744004221 | F39: pdf | G39: 46077 | H39: RAPDF | I39: 100 | J39: =IF(I39="","Rapport manquant",IF(I39>=85,"CONFORME (≥85%)","NON CONFORME (<85%)")) | K39: 15 | L39: 0 | M39: 31 | P39: 5 | Q39: 5 | R39: 0 | S39: 0 | T39: 0 | U39: 0 | V39: 0 | W39: 0 | X39: 1.8333333 | Y39: 1.8333333 | Z39: 1 | AA39: 1
A40: Hiba LISSAOUI | B40: 2026 | C40: 9 | D40: =B40&"-S"&TEXT(C40,"00") | E40: EMP_9902030152_011000767923078 | F40: pdf | G40: 46078 | H40: RAPDF | I40: 100 | J40: =IF(I40="","À saisir",IF(I40>=85,"CONFORME (≥85%)","NON CONFORME (<85%)")) | K40: 14 | L40: 0 | M40: 30 | N40: 3.1 – Chaque tableau de données complexe a-t-il une alternative ? 3.2 – Pour chaque tableau de données complexe ayant une alternative, cette alternative est-elle pertinente ? | P40: 5 | Q40: 5 | R40: 0 | S40: 0 | T40: 0 | U40: 0 | V40: 0 | W40: 0 | X40: 1.8333333 | Y40: 1.8333333 | Z40: 1 | AA40: 1
A41: Imad RMAIDI | B41: 2026 | C41: 9 | D41: =B41&"-S"&TEXT(C41,"00") | E41: SAN_9902030040_011000804912294 | F41: pdf | G41: 46076 | H41: RAPDF | I41: 100 | J41: =IF(I41="","À saisir",IF(I41>=85,"CONFORME (≥85%)","NON CONFORME (<85%)")) | K41: 12 | L41: 0 | M41: 28 | P41: 5 | Q41: 5 | R41: 0 | S41: 0 | T41: 0 | U41: 0 | V41: 0 | W41: 0 | X41: 1.8333333 | Y41: 1.8333333 | Z41: 1 | AA41: 1
A42: Mohamed HAMDANI | B42: 2026 | C42: 9 | D42: =B42&"-S"&TEXT(C42,"00") | E42: SAN_9902030030_011000710963677 | F42: pdf | G42: 46078 | H42: RAPDF | I42: 100 | J42: =IF(I42="","À saisir",IF(I42>=85,"CONFORME (≥85%)","NON CONFORME (<85%)")) | K42: 13 | L42: 0 | M42: 33 | P42: 5 | Q42: 5 | R42: 0 | S42: 0 | T42: 0 | U42: 0 | V42: 0 | W42: 0 | X42: 1.8333333 | Y42: 1.8333333 | Z42: 1 | AA42: 1
A43: Hafssa BENCHRIF | B43: 2026 | C43: 10 | D43: =B43&"-S"&TEXT(C43,"00") | E43: COL_9902030098_011000764636583 | F43: pdf | G43: 46084 | H43: RAPDF | I43: 93.3 | J43: =IF(I43="","Rapport manquant",IF(I43>=85,"CONFORME (≥85%)","NON CONFORME (<85%)")) | K43: 14 | L43: 1 | M43: 31 | N43: 6.3 – Chaque lien, indiqué uniquement par la couleur et dont la nature n'est pas évidente, est-il visible par rapport au texte environnant ? (le lien n'est pas souligné et pas bien contraster) | O43: Debrief de l’agent pour le sensibiliser à l’importance d’être vigilant sur le traitement, puis exercice pratique avec l’ensemble de l’équipe. | P43: 5 | Q43: 5 | R43: 0 | S43: 0 | T43: 0 | U43: 0 | V43: 0 | W43: 0 | X43: 1.8333333 | Y43: 1.8333333 | Z43: 1 | AA43: 1
A44: Hiba LISSAOUI | B44: 2026 | C44: 10 | D44: =B44&"-S"&TEXT(C44,"00") | E44: EMP_9902030152_011000767923080 | F44: pdf | G44: 46085 | H44: RAPDF | I44: 100 | J44: =IF(I44="","À saisir",IF(I44>=85,"CONFORME (≥85%)","NON CONFORME (<85%)")) | K44: 16 | L44: 0 | M44: 30 | P44: 5 | Q44: 5 | R44: 0 | S44: 0 | T44: 0 | U44: 0 | V44: 0 | W44: 0 | X44: 1.8333333 | Y44: 1.8333333 | Z44: 1 | AA44: 1
A45: Imad RMAIDI | B45: 2026 | C45: 10 | D45: =B45&"-S"&TEXT(C45,"00") | E45: SAN_9902030030_011000710963708 | F45: pdf | G45: 46084 | H45: RAPDF | I45: 100 | J45: =IF(I45="","À saisir",IF(I45>=85,"CONFORME (≥85%)","NON CONFORME (<85%)")) | K45: 15 | L45: 0 | M45: 31 | P45: 5 | Q45: 5 | R45: 0 | S45: 0 | T45: 0 | U45: 0 | V45: 0 | W45: 0 | X45: 1.8333333 | Y45: 1.8333333 | Z45: 1 | AA45: 1
A46: Mohamed HAMDANI | B46: 2026 | C46: 10 | D46: =B46&"-S"&TEXT(C46,"00") | E46: SAN_9902030030_011000710963634 | F46: pdf | G46: 46086 | H46: RAPDF | I46: 100 | J46: =IF(I46="","À saisir",IF(I46>=85,"CONFORME (≥85%)","NON CONFORME (<85%)")) | K46: 13 | L46: 0 | M46: 33 | P46: 5 | Q46: 5 | R46: 0 | S46: 0 | T46: 0 | U46: 0 | V46: 0 | W46: 0 | X46: 1.8333333 | Y46: 1.8333333 | Z46: 1 | AA46: 1
A47: Hafssa BENCHRIF | B47: 2026 | C47: 11 | D47: =B47&"-S"&TEXT(C47,"00") | E47: FGDR10278 | F47: pdf | G47: 46094 | H47: RAPDF | I47: 100 | J47: =IF(I47="","Rapport manquant",IF(I47>=85,"CONFORME (≥85%)","NON CONFORME (<85%)")) | K47: 14 | L47: 0 | M47: 32 | P47: 5 | Q47: 5 | R47: 0 | S47: 0 | T47: 0 | U47: 0 | V47: 0 | W47: 0 | X47: 1.8333333 | Y47: 1.8333333 | Z47: 1 | AA47: 1
A48: Hiba LISSAOUI | B48: 2026 | C48: 11 | D48: =B48&"-S"&TEXT(C48,"00") | E48: CM.05.32 | F48: pdf | G48: 46093 | H48: RAPDF | I48: 100 | J48: =IF(I48="","À saisir",IF(I48>=85,"CONFORME (≥85%)","NON CONFORME (<85%)")) | K48: 10 | L48: 0 | M48: 36 | P48: 5 | Q48: 5 | R48: 0 | S48: 0 | T48: 0 | U48: 0 | V48: 0 | W48: 0 | X48: 1.8333333 | Y48: 1.8333333 | Z48: 1 | AA48: 1
A49: Imad RMAIDI | B49: 2026 | C49: 11 | D49: =B49&"-S"&TEXT(C49,"00") | E49: SAN_9902020008_011000745243123 | F49: pdf | H49: — | J49: =IF(I49="","À saisir",IF(I49>=85,"CONFORME (≥85%)","NON CONFORME (<85%)")) | P49: 5 | Q49: 5 | R49: 0 | S49: 0 | T49: 0 | U49: 0 | V49: 0 | W49: 0 | X49: 1.8333333 | Y49: 1.8333333 | Z49: 1 | AA49: 1
A50: Mohamed HAMDANI | B50: 2026 | C50: 11 | D50: =B50&"-S"&TEXT(C50,"00") | E50: SAN_9902030053_011000789059347 | F50: pdf | H50: — | J50: =IF(I50="","À saisir",IF(I50>=85,"CONFORME (≥85%)","NON CONFORME (<85%)")) | P50: 5 | Q50: 5 | R50: 0 | S50: 0 | T50: 0 | U50: 0 | V50: 0 | W50: 0 | X50: 1.8333333 | Y50: 1.8333333 | Z50: 1 | AA50: 1
A51: Hafssa BENCHRIF | B51: 2026 | C51: 12 | D51: =B51&"-S"&TEXT(C51,"00") | E51: 81.69.55 | F51: pdf | G51: 46100 | H51: RAPDF | I51: 100 | J51: =IF(I51="","Rapport manquant",IF(I51>=85,"CONFORME (≥85%)","NON CONFORME (<85%)")) | K51: 18 | L51: 0 | M51: 28 | P51: 0 | Q51: 0 | R51: 0 | S51: 0 | T51: 0 | U51: 0 | V51: 0 | W51: 0 | X51: 0 | Y51: 0
A52: Hiba LISSAOUI | B52: 2026 | C52: 12 | D52: =B52&"-S"&TEXT(C52,"00") | E52: 16.61.12 notice | F52: pdf | G52: 46100 | H52: RAPDF | I52: 100 | J52: =IF(I52="","À saisir",IF(I52>=85,"CONFORME (≥85%)","NON CONFORME (<85%)")) | K52: 14 | L52: 0 | M52: 32 | P52: 0 | Q52: 0 | R52: 0 | S52: 0 | T52: 0 | U52: 0 | V52: 0 | W52: 0 | X52: 0 | Y52: 0
A53: Imad RMAIDI | B53: 2026 | C53: 12 | D53: =B53&"-S"&TEXT(C53,"00") | E53: (à saisir) | H53: — | J53: =IF(I53="","À saisir",IF(I53>=85,"CONFORME (≥85%)","NON CONFORME (<85%)")) | P53: 0 | Q53: 0 | R53: 0 | S53: 0 | T53: 0 | U53: 0 | V53: 0 | W53: 0 | X53: 0 | Y53: 0
A54: Mohamed HAMDANI | B54: 2026 | C54: 12 | D54: =B54&"-S"&TEXT(C54,"00") | E54: DIT10278 | F54: pdf | G54: 46100 | H54: RAPDF | I54: 100 | J54: =IF(I54="","À saisir",IF(I54>=85,"CONFORME (≥85%)","NON CONFORME (<85%)")) | K54: 13 | L54: 0 | M54: 33 | P54: 0 | Q54: 0 | R54: 0 | S54: 0 | T54: 0 | U54: 0 | V54: 0 | W54: 0 | X54: 0 | Y54: 0
A55: Hafssa BENCHRIF | B55: 2026 | C55: 16 | D55: =B55&"-S"&TEXT(C55,"00") | E55: 9800059279 Fc_E-Retrait_v062026 | F55: word | H55: — | J55: =IF(I55="","Rapport manquant",IF(I55>=85,"CONFORME (≥85%)","NON CONFORME (<85%)")) | P55: 3 | Q55: 3 | R55: 0 | S55: 0 | T55: 2 | U55: 0 | V55: 0 | W55: 0 | X55: 1.0833333 | Y55: 1.0833333 | Z55: 1 | AA55: 1
A56: Hiba LISSAOUI | B56: 2026 | C56: 16 | D56: =B56&"-S"&TEXT(C56,"00") | E56: 9800155243 Fc_CB_MC_Vie_Quotidienne_v062026 | F56: word | G56: 46129 | H56: RAPDF | I56: 100 | J56: =IF(I56="","À saisir",IF(I56>=85,"CONFORME (≥85%)","NON CONFORME (<85%)")) | K56: 20 | L56: 0 | M56: 26 | P56: 5 | Q56: 5 | R56: 0 | S56: 0 | T56: 0 | U56: 0 | V56: 0 | W56: 0 | X56: 1.8333333 | Y56: 1.8333333 | Z56: 1 | AA56: 1
A57: Imad RMAIDI | B57: 2026 | C57: 16 | D57: =B57&"-S"&TEXT(C57,"00") | E57: 9800103268 Fz_CB_MC_Gold_Devise_v062026 | F57: word | G57: 46129 | H57: RAPDF | I57: 100 | J57: =IF(I57="","À saisir",IF(I57>=85,"CONFORME (≥85%)","NON CONFORME (<85%)")) | K57: 17 | L57: 0 | M57: 29 | P57: 5 | Q57: 5 | R57: 0 | S57: 0 | T57: 0 | U57: 0 | V57: 0 | W57: 0 | X57: 1.8333333 | Y57: 1.8333333 | Z57: 1 | AA57: 1
A58: Mohamed HAMDANI | B58: 2026 | C58: 16 | D58: =B58&"-S"&TEXT(C58,"00") | E58: 9800166677 Fz_Apple_Pay_v062026 | F58: word | G58: 46129 | H58: RAPDF | I58: 100 | J58: =IF(I58="","À saisir",IF(I58>=85,"CONFORME (≥85%)","NON CONFORME (<85%)")) | K58: 15 | L58: 0 | M58: 31 | P58: 5 | Q58: 5 | R58: 0 | S58: 0 | T58: 0 | U58: 0 | V58: 0 | W58: 0 | X58: 1.8333333 | Y58: 1.8333333 | Z58: 1 | AA58: 1
A59: Hiba LISSAOUI | B59: 2026 | C59: 17 | D59: =B59&"-S"&TEXT(C59,"00") | E59: 9800165798 Fc_CB_MC_Gold_Certizen_v062026 | F59: word | G59: 46135 | H59: RAPDF | I59: 100 | J59: =IF(I59="","À saisir",IF(I59>=85,"CONFORME (≥85%)","NON CONFORME (<85%)")) | K59: 18 | L59: 0 | M59: 28 | P59: 5 | Q59: 5 | R59: 0 | S59: 0 | T59: 0 | U59: 0 | V59: 0 | W59: 0 | X59: 1.8333333 | Y59: 1.8333333 | Z59: 1 | AA59: 1
A60: Imad RMAIDI | B60: 2026 | C60: 17 | D60: =B60&"-S"&TEXT(C60,"00") | E60: 9800182914 CM FC compte courant PART | F60: word | G60: 46136 | H60: RAPDF | I60: 100 | J60: =IF(I60="","À saisir",IF(I60>=85,"CONFORME (≥85%)","NON CONFORME (<85%)")) | K60: 13 | L60: 0 | M60: 33 | P60: 4 | Q60: 3 | R60: 1 | S60: 0 | T60: 1 | U60: 0 | V60: 0 | W60: 0 | X60: 1.4583333 | Y60: 1.0833333 | Z60: 0.75 | AA60: 0.74285714
A61: Mohamed HAMDANI | B61: 2026 | C61: 17 | D61: =B61&"-S"&TEXT(C61,"00") | E61: Fiche Zoom Alertes CIC revue | F61: word | G61: 46136 | H61: RAPDF | I61: 100 | J61: =IF(I61="","À saisir",IF(I61>=85,"CONFORME (≥85%)","NON CONFORME (<85%)")) | K61: 16 | L61: 0 | M61: 30 | P61: 5 | Q61: 5 | R61: 0 | S61: 0 | T61: 0 | U61: 0 | V61: 0 | W61: 0 | X61: 1.8333333 | Y61: 1.8333333 | Z61: 1 | AA61: 1
A62: Hiba LISSAOUI | B62: 2026 | C62: 18 | D62: =B62&"-S"&TEXT(C62,"00") | E62: 0110017197 Fc_CB_Visa_Classic_v062026 | F62: word | G62: 46143 | H62: RAPDF | I62: 100 | J62: =IF(I62="","À saisir",IF(I62>=85,"CONFORME (≥85%)","NON CONFORME (<85%)")) | K62: 19 | L62: 0 | M62: 27 | P62: 4 | Q62: 4 | R62: 0 | S62: 0 | T62: 0 | U62: 1 | V62: 0 | W62: 0 | X62: 1.5 | Y62: 1.5 | Z62: 1 | AA62: 1
A63: Imad RMAIDI | B63: 2026 | C63: 18 | D63: =B63&"-S"&TEXT(C63,"00") | E63: 9800164541 CM - Digipass | F63: word | G63: 46143 | H63: RAPDF | I63: 100 | J63: =IF(I63="","À saisir",IF(I63>=85,"CONFORME (≥85%)","NON CONFORME (<85%)")) | K63: 13 | L63: 0 | M63: 33 | P63: 4 | Q63: 4 | R63: 0 | S63: 0 | T63: 0 | U63: 1 | V63: 0 | W63: 0 | X63: 1.5 | Y63: 1.5 | Z63: 1 | AA63: 1
A64: Mohamed HAMDANI | B64: 2026 | C64: 18 | D64: =B64&"-S"&TEXT(C64,"00") | E64: PdB 9800135222 | F64: word | G64: 46142 | H64: RAPDF | I64: 100 | J64: =IF(I64="","À saisir",IF(I64>=85,"CONFORME (≥85%)","NON CONFORME (<85%)")) | K64: 16 | L64: 0 | M64: 30 | P64: 4 | Q64: 4 | R64: 0 | S64: 0 | T64: 0 | U64: 1 | V64: 0 | W64: 0 | X64: 1.5 | Y64: 1.5 | Z64: 1 | AA64: 1
A65: Hiba LISSAOUI | B65: 2026 | C65: 19 | D65: =B65&"-S"&TEXT(C65,"00") | E65: 9800222734 FZ compte courant sequestre judiciaire | F65: word | G65: 46146 | H65: RAPDF | I65: 100 | J65: =IF(I65="","À saisir",IF(I65>=85,"CONFORME (≥85%)","NON CONFORME (<85%)")) | K65: 16 | L65: 0 | M65: 30 | P65: 4 | Q65: 4 | R65: 0 | S65: 0 | T65: 0 | U65: 0 | V65: 0 | W65: 0 | X65: 1.5 | Y65: 1.5 | Z65: 1 | AA65: 1
A66: Imad RMAIDI | B66: 2026 | C66: 19 | D66: =B66&"-S"&TEXT(C66,"00") | E66: 9800075418 CM - EUC Vie Quotidienne 2025 | F66: word | G66: 46146 | H66: RAPDF | I66: 100 | J66: =IF(I66="","À saisir",IF(I66>=85,"CONFORME (≥85%)","NON CONFORME (<85%)")) | K66: 13 | L66: 0 | M66: 33 | P66: 4 | Q66: 4 | R66: 0 | S66: 0 | T66: 0 | U66: 0 | V66: 0 | W66: 0 | X66: 1.5 | Y66: 1.5 | Z66: 1 | AA66: 1
A67: Mohamed HAMDANI | B67: 2026 | C67: 19 | D67: =B67&"-S"&TEXT(C67,"00") | E67: 9800222734 FZ compte courant séquestre judiciaire | F67: word | G67: 46146 | H67: RAPDF | I67: 100 | J67: =IF(I67="","À saisir",IF(I67>=85,"CONFORME (≥85%)","NON CONFORME (<85%)")) | K67: 16 | L67: 0 | M67: 30 | P67: 4 | Q67: 4 | R67: 0 | S67: 0 | T67: 0 | U67: 0 | V67: 0 | W67: 0 | X67: 1.5 | Y67: 1.5 | Z67: 1 | AA67: 1
... A80: Imad RMAIDI | B80: 2026 | C80: 24 | D80: =B80&"-S"&TEXT(C80,"00") | E80: P1_Notice_Cofidis-France_10-2026 | F80: pdf | G80: 46182 | H80: RAPDF | I80: 100 | J80: =IF(I80="","À saisir",IF(I80>=85,"CONFORME (≥85%)","NON CONFORME (<85%)")) | K80: 13 | L80: 0 | M80: 33 | P80: 5 | Q80: 5 | R80: 0 | S80: 0 | T80: 0 | U80: 0 | V80: 0 | W80: 0 | X80: 1.8333333 | Y80: 1.8333333 | Z80: 1 | AA80: 1
A81: Mohamed HAMDANI | B81: 2026 | C81: 24 | D81: =B81&"-S"&TEXT(C81,"00") | E81: P1_IPID_Monabanq_10-2026 | F81: pdf | G81: 46182 | H81: RAPDF | I81: 92.9 | J81: =IF(I81="","À saisir",IF(I81>=85,"CONFORME (≥85%)","NON CONFORME (<85%)")) | K81: 13 | L81: 1 | M81: 32 | N81: 2.2 – Le contraste entre la couleur du texte et la couleur de son arrière-plan est-il suffisamment élevé ? (LE contraste des puces "point d'exclamation" est NON-CONFORME) | O81: Debrief de l’agent pour le sensibiliser à l’importance d’être vigilant sur le traitement, puis exercice pratique avec l’ensemble de l’équipe. | P81: 5 | Q81: 5 | R81: 0 | S81: 0 | T81: 0 | U81: 0 | V81: 0 | W81: 0 | X81: 1.8333333 | Y81: 1.8333333 | Z81: 1 | AA81: 1
A82: Hiba LISSAOUI | B82: 2026 | C82: 25 | D82: =B82&"-S"&TEXT(C82,"00") | E82: 0130015514_FC Tonic Privilège à préavis_072026 | F82: pdf | G82: 46231 | H82: RAPDF | I82: 100 | J82: =IF(I82="","À saisir",IF(I82>=85,"CONFORME (≥85%)","NON CONFORME (<85%)")) | K82: 16 | L82: 0 | M82: 30 | P82: 5 | Q82: 5 | R82: 0 | S82: 0 | T82: 0 | U82: 0 | V82: 0 | W82: 0 | X82: 1.8333333 | Y82: 1.8333333 | Z82: 1 | AA82: 1
A83: Imad RMAIDI | B83: 2026 | C83: 25 | D83: =B83&"-S"&TEXT(C83,"00") | E83: 0130022152_FC Tonic Plus_072026 | F83: word | G83: 46189 | H83: RAPDF | I83: 100 | J83: =IF(I83="","À saisir",IF(I83>=85,"CONFORME (≥85%)","NON CONFORME (<85%)")) | K83: 13 | L83: 0 | M83: 33 | P83: 4 | Q83: 4 | R83: 0 | S83: 0 | T83: 1 | U83: 0 | V83: 0 | W83: 0 | X83: 1.5 | Y83: 1.5 | Z83: 1 | AA83: 1
A84: Mohamed HAMDANI | B84: 2026 | C84: 25 | D84: =B84&"-S"&TEXT(C84,"00") | E84: 0130018095_FC CM ADD_072026 | F84: pdf | G84: 46189 | H84: RAPDF | I84: 100 | J84: =IF(I84="","À saisir",IF(I84>=85,"CONFORME (≥85%)","NON CONFORME (<85%)")) | K84: 14 | L84: 0 | M84: 32 | P84: 5 | Q84: 5 | R84: 0 | S84: 0 | T84: 0 | U84: 0 | V84: 0 | W84: 0 | X84: 1.8333333 | Y84: 1.8333333 | Z84: 1 | AA84: 1
A85: Hiba LISSAOUI | B85: 2026 | C85: 26 | D85: =B85&"-S"&TEXT(C85,"00") | E85: 0130024381_FC_Wero _072026 | F85: word | G85: 46195 | H85: RAPDF | I85: 100 | J85: =IF(I85="","À saisir",IF(I85>=85,"CONFORME (≥85%)","NON CONFORME (<85%)")) | K85: 17 | L85: 0 | M85: 29 | P85: 5 | Q85: 5 | R85: 0 | S85: 0 | T85: 0 | U85: 0 | V85: 0 | W85: 0 | X85: 1.8333333 | Y85: 1.8333333 | Z85: 1 | AA85: 1
A86: Imad RMAIDI | B86: 2026 | C86: 26 | D86: =B86&"-S"&TEXT(C86,"00") | E86: 0130025139 Fc_Payweb_Card_v072026 | F86: word | G86: 46196 | H86: RAPDF | I86: 100 | J86: =IF(I86="","À saisir",IF(I86>=85,"CONFORME (≥85%)","NON CONFORME (<85%)")) | K86: 13 | L86: 0 | M86: 33 | P86: 5 | Q86: 5 | R86: 0 | S86: 0 | T86: 0 | U86: 0 | V86: 0 | W86: 0 | X86: 1.8333333 | Y86: 1.8333333 | Z86: 1 | AA86: 1
A87: Mohamed HAMDANI | B87: 2026 | C87: 26 | D87: =B87&"-S"&TEXT(C87,"00") | E87: 0130009109 CM - Eurocompte jeune 072026 | F87: pdf | G87: 46196 | H87: RAPDF | I87: 100 | J87: =IF(I87="","À saisir",IF(I87>=85,"CONFORME (≥85%)","NON CONFORME (<85%)")) | K87: 14 | L87: 0 | M87: 32 | P87: 5 | Q87: 5 | R87: 0 | S87: 0 | T87: 0 | U87: 0 | V87: 1 | W87: 51 | X87: 1.8333333 | Y87: 1.8333333 | Z87: 1 | AA87: 1
A88: Hiba LISSAOUI | B88: 2026 | C88: 27 | D88: =B88&"-S"&TEXT(C88,"00") | E88: COL_9902030098_011000823633463 | F88: pdf | G88: 46203 | H88: RAPDF | I88: 100 | J88: =IF(I88="","À saisir",IF(I88>=85,"CONFORME (≥85%)","NON CONFORME (<85%)")) | K88: 13 | L88: 0 | M88: 33 | P88: 5 | Q88: 5 | R88: 0 | S88: 0 | T88: 0 | U88: 0 | V88: 0 | W88: 0 | X88: 1.8333333 | Y88: 1.8333333 | Z88: 1 | AA88: 1
A89: Imad RMAIDI | B89: 2026 | C89: 27 | D89: =B89&"-S"&TEXT(C89,"00") | E89: COL_9902030098_011000823633466 | F89: pdf | G89: 46204 | H89: RAPDF | I89: 100 | J89: =IF(I89="","À saisir",IF(I89>=85,"CONFORME (≥85%)","NON CONFORME (<85%)")) | K89: 12 | L89: 0 | M89: 34 | P89: 5 | Q89: 5 | R89: 0 | S89: 0 | T89: 0 | U89: 0 | V89: 0 | W89: 0 | X89: 1.8333333 | Y89: 1.8333333 | Z89: 1 | AA89: 1
A90: Mohamed HAMDANI | B90: 2026 | C90: 27 | D90: =B90&"-S"&TEXT(C90,"00") | E90: COL_9902030092_011000709664942 | F90: pdf | G90: 46203 | H90: RAPDF | I90: 100 | J90: =IF(I90="","À saisir",IF(I90>=85,"CONFORME (≥85%)","NON CONFORME (<85%)")) | K90: 13 | L90: 0 | M90: 33 | P90: 5 | Q90: 5 | R90: 0 | S90: 0 | T90: 0 | U90: 0 | V90: 0 | W90: 0 | X90: 1.8333333 | Y90: 1.8333333 | Z90: 1 | AA90: 1
A91: Hiba LISSAOUI | B91: 2026 | C91: 28 | D91: =B91&"-S"&TEXT(C91,"00") | E91: IRD_9902030015_011000527904321 | F91: pdf | G91: 46210 | H91: RAPDF | I91: 100 | J91: =IF(I91="","À saisir",IF(I91>=85,"CONFORME (≥85%)","NON CONFORME (<85%)")) | K91: 14 | L91: 0 | M91: 32 | P91: 5 | Q91: 5 | R91: 0 | S91: 0 | T91: 0 | U91: 0 | V91: 0 | W91: 0 | X91: 1.8333333 | Y91: 1.8333333 | Z91: 1 | AA91: 1
A92: Imad RMAIDI | B92: 2026 | C92: 28 | D92: =B92&"-S"&TEXT(C92,"00") | E92: IRD_9902030015_011000527904323 | F92: pdf | G92: 46211 | H92: RAPDF | I92: 100 | J92: =IF(I92="","À saisir",IF(I92>=85,"CONFORME (≥85%)","NON CONFORME (<85%)")) | K92: 13 | L92: 0 | M92: 33 | P92: 5 | Q92: 5 | R92: 0 | S92: 0 | T92: 0 | U92: 0 | V92: 0 | W92: 0 | X92: 1.8333333 | Y92: 1.8333333 | Z92: 1 | AA92: 1
A93: Mohamed HAMDANI | B93: 2026 | C93: 28 | D93: =B93&"-S"&TEXT(C93,"00") | E93: IRD_9902030015_011000527904322 | F93: pdf | G93: 46210 | H93: RAPDF | I93: 100 | J93: =IF(I93="","À saisir",IF(I93>=85,"CONFORME (≥85%)","NON CONFORME (<85%)")) | K93: 14 | L93: 0 | M93: 32 | P93: 5 | Q93: 5 | R93: 0 | S93: 0 | T93: 0 | U93: 0 | V93: 0 | W93: 0 | X93: 1.8333333 | Y93: 1.8333333 | Z93: 1 | AA93: 1
A94: Hiba LISSAOUI | B94: 2026 | C94: 29 | D94: =B94&"-S"&TEXT(C94,"00") | E94: PJU_9902030015_011000715122529 | F94: pdf | G94: 46220 | H94: RAPDF | I94: 92.3 | J94: =IF(I94="","À saisir",IF(I94>=85,"CONFORME (≥85%)","NON CONFORME (<85%)")) | K94: 12 | L94: 1 | M94: 33 | N94: 2.2 – Le contraste entre la couleur du texte et la couleur de son arrière-plan est-il suffisamment élevé ? (Le Ratio d e contraste des puces n'est pas conforme "car il s'adit d'un document IPID") | O94: Debrief de l’agent pour le sensibiliser à l’importance d’être vigilant sur le traitement, puis exercice pratique avec l’ensemble de l’équipe. | P94: 4 | Q94: 4 | R94: 0 | S94: 0 | T94: 0 | U94: 0 | V94: 0 | W94: 0 | X94: 1.4583333 | Y94: 1.4583333 | Z94: 1 | AA94: 1
A95: Imad RMAIDI | B95: 2026 | C95: 29 | D95: =B95&"-S"&TEXT(C95,"00") | E95: IRD_9902030015_011000882672599 | F95: pdf | G95: 46217 | H95: RAPDF | I95: 100 | J95: =IF(I95="","À saisir",IF(I95>=85,"CONFORME (≥85%)","NON CONFORME (<85%)")) | K95: 16 | L95: 0 | M95: 30 | P95: 4 | Q95: 4 | R95: 0 | S95: 0 | T95: 0 | U95: 0 | V95: 0 | W95: 0 | X95: 1.4583333 | Y95: 1.4583333 | Z95: 1 | AA95: 1
A96: Hiba LISSAOUI | B96: 2026 | C96: 30 | D96: =B96&"-S"&TEXT(C96,"00") | E96: FC Compte courant basic | F96: word | G96: 46224 | H96: RAPDF | I96: 100 | J96: =IF(I96="","À saisir",IF(I96>=85,"CONFORME (≥85%)","NON CONFORME (<85%)")) | K96: 15 | L96: 0 | M96: 31 | P96: 5 | Q96: 5 | R96: 0 | S96: 0 | T96: 0 | U96: 0 | V96: 0 | W96: 0 | X96: 1.8333333 | Y96: 1.8333333 | Z96: 1 | AA96: 1
A97: Imad RMAIDI | B97: 2026 | C97: 30 | D97: =B97&"-S"&TEXT(C97,"00") | E97: FC capital expansion 07 2026 | F97: pdf | G97: 46225 | H97: RAPDF | I97: 100 | J97: =IF(I97="","À saisir",IF(I97>=85,"CONFORME (≥85%)","NON CONFORME (<85%)")) | K97: 13 | L97: 0 | M97: 33 | P97: 5 | Q97: 5 | R97: 0 | S97: 0 | T97: 0 | U97: 0 | V97: 0 | W97: 0 | X97: 1.8333333 | Y97: 1.8333333 | Z97: 1 | AA97: 1
A98: Mohamed HAMDANI | B98: 2026 | C98: 30 | D98: =B98&"-S"&TEXT(C98,"00") | E98: FC LIVRET JEUNE 07 2026 | F98: pdf | G98: 46224 | H98: RAPDF | I98: 100 | J98: =IF(I98="","À saisir",IF(I98>=85,"CONFORME (≥85%)","NON CONFORME (<85%)")) | K98: 16 | L98: 0 | M98: 30 | P98: 4 | Q98: 4 | R98: 0 | S98: 0 | T98: 1 | U98: 0 | V98: 0 | W98: 0 | X98: 1.5 | Y98: 1.5 | Z98: 1 | AA98: 1
A99: Hiba LISSAOUI | B99: 2026 | C99: 31 | D99: =B99&"-S"&TEXT(C99,"00") | E99: IRD_9902030015_011000527904322 | F99: pdf | G99: 46231 | H99: RAPDF | I99: 100 | J99: =IF(I99="","À saisir",IF(I99>=85,"CONFORME (≥85%)","NON CONFORME (<85%)")) | K99: 14 | L99: 0 | M99: 32 | P99: 4 | Q99: 4 | R99: 0 | S99: 0 | T99: 1 | U99: 0 | V99: 0 | W99: 0 | X99: 1.4583333 | Y99: 1.4583333 | Z99: 1 | AA99: 1
A100: Imad RMAIDI | B100: 2026 | C100: 31 | D100: =B100&"-S"&TEXT(C100,"00") | E100: IRD_9902030015_011000527904325 | F100: pdf | G100: 46232 | H100: RAPDF | I100: 100 | J100: =IF(I100="","À saisir",IF(I100>=85,"CONFORME (≥85%)","NON CONFORME (<85%)")) | K100: 16 | L100: 0 | M100: 30 | P100: 5 | Q100: 5 | R100: 0 | S100: 0 | T100: 0 | U100: 0 | V100: 0 | W100: 0 | X100: 1.8333333 | Y100: 1.8333333 | Z100: 1 | AA100: 1
A101: Mohamed HAMDANI | B101: 2026 | C101: 31 | D101: =B101&"-S"&TEXT(C101,"00") | E101: 0470005537 CIC - FZ Parcours J | F101: pdf | G101: 46231 | H101: RAPDF | I101: 100 | J101: =IF(I101="","À saisir",IF(I101>=85,"CONFORME (≥85%)","NON CONFORME (<85%)")) | K101: 14 | L101: 0 | M101: 32 | P101: 5 | Q101: 5 | R101: 0 | S101: 0 | T101: 0 | U101: 0 | V101: 0 | W101: 0 | X101: 1.8333333 | Y101: 1.8333333 | Z101: 1 | AA101: 1
A102: Hiba LISSAOUI | B102: 2026 | C102: 32 | D102: =B102&"-S"&TEXT(C102,"00") | E102: IRD_9902030015_011000625586072 | F102: pdf | G102: 46237 | H102: RAPDF | I102: 100 | J102: =IF(I102="","À saisir",IF(I102>=85,"CONFORME (≥85%)","NON CONFORME (<85%)")) | K102: 18 | L102: 0 | M102: 28 | P102: 5 | Q102: 5 | R102: 0 | S102: 0 | T102: 0 | U102: 0 | V102: 0 | W102: 0 | X102: 1.8333333 | Y102: 1.8333333 | Z102: 1 | AA102: 1
A103: Imad RMAIDI | B103: 2026 | C103: 32 | D103: =B103&"-S"&TEXT(C103,"00") | E103: IRD_9902030015_011000625586081 | F103: pdf | G103: 46241 | H103: RAPDF | I103: 100 | J103: =IF(I103="","À saisir",IF(I103>=85,"CONFORME (≥85%)","NON CONFORME (<85%)")) | K103: 18 | L103: 0 | M103: 28 | P103: 5 | Q103: 5 | R103: 0 | S103: 0 | T103: 0 | U103: 0 | V103: 0 | W103: 0 | X103: 1.8333333 | Y103: 1.8333333 | Z103: 1 | AA103: 1
A104: Mohamed HAMDANI | B104: 2026 | C104: 32 | D104: =B104&"-S"&TEXT(C104,"00") | E104: IRD_9902030015_011000586849369 | F104: pdf | G104: 46243 | H104: RAPDF | I104: 92.3 | J104: =IF(I104="","À saisir",IF(I104>=85,"CONFORME (≥85%)","NON CONFORME (<85%)")) | K104: 12 | L104: 1 | M104: 33 | N104: 2.2 – Le contraste entre la couleur du texte et la couleur de son arrière-plan est-il suffisamment élevé ? ([Commentaire source] Le ratio de contraste sur les textes doit être respecté. Remarque concernant les documents dont la forme est régie par une réglementation (Cerfa...) : il déroge à ce critère si une norme ou une loi l'y oblige.) | O104: Debrief de l’agent pour le sensibiliser à l’importance d’être vigilant sur le traitement, puis exercice pratique avec l’ensemble de l’équipe. | P104: 5 | Q104: 5 | R104: 0 | S104: 0 | T104: 0 | U104: 0 | V104: 1 | W104: 21 | X104: 1.8333333 | Y104: 1.8333333 | Z104: 1 | AA104: 1
A105: Hiba LISSAOUI | B105: 2026 | C105: 33 | D105: =B105&"-S"&TEXT(C105,"00") | E105: 9800207241_FC Credit Vélo | F105: pdf | G105: 46249 | H105: RAPDF | I105: 100 | J105: =IF(I105="","À saisir",IF(I105>=85,"CONFORME (≥85%)","NON CONFORME (<85%)")) | K105: 13 | L105: 0 | M105: 33 | P105: 5 | Q105: 5 | R105: 0 | S105: 0 | T105: 0 | U105: 0 | V105: 0 | W105: 0 | X105: 1.8333333 | Y105: 1.8333333 | Z105: 1 | AA105: 1
A106: Imad RMAIDI | B106: 2026 | C106: 33 | D106: =B106&"-S"&TEXT(C106,"00") | E106: 2026 FC Top infos | F106: pdf | G106: 46244 | H106: RAPDF | I106: 100 | J106: =IF(I106="","À saisir",IF(I106>=85,"CONFORME (≥85%)","NON CONFORME (<85%)")) | K106: 15 | L106: 0 | M106: 31 | P106: 5 | Q106: 5 | R106: 0 | S106: 0 | T106: 0 | U106: 0 | V106: 0 | W106: 0 | X106: 1.8333333 | Y106: 1.8333333 | Z106: 1 | AA106: 1
A107: Mohamed HAMDANI | B107: 2026 | C107: 33 | D107: =B107&"-S"&TEXT(C107,"00") | E107: 9800133888_FZ Start etudiant entrepreneurs | F107: pdf | G107: 46247 | H107: RAPDF | I107: 100 | J107: =IF(I107="","À saisir",IF(I107>=85,"CONFORME (≥85%)","NON CONFORME (<85%)")) | K107: 14 | L107: 0 | M107: 32 | P107: 5 | Q107: 5 | R107: 0 | S107: 0 | T107: 0 | U107: 0 | V107: 0 | W107: 0 | X107: 1.8333333 | Y107: 1.8333333 | Z107: 1 | AA107: 1
A108: Hiba LISSAOUI | B108: 2026 | C108: 34 | D108: =B108&"-S"&TEXT(C108,"00") | E108: 9800242964 fiche clarté CREDIT REBOND | F108: pdf | G108: 46251 | H108: RAPDF | I108: 100 | J108: =IF(I108="","À saisir",IF(I108>=85,"CONFORME (≥85%)","NON CONFORME (<85%)")) | K108: 13 | L108: 0 | M108: 33 | P108: 5 | Q108: 5 | R108: 0 | S108: 0 | T108: 0 | U108: 0 | V108: 0 | W108: 0 | X108: 1.8333333 | Y108: 1.8333333 | Z108: 1 | AA108: 1
A109: Imad RMAIDI | B109: 2026 | C109: 34 | D109: =B109&"-S"&TEXT(C109,"00") | E109: 9800223162_Fiche Clarté Multiprojets | F109: pdf | G109: 46256 | H109: RAPDF | I109: 100 | J109: =IF(I109="","À saisir",IF(I109>=85,"CONFORME (≥85%)","NON CONFORME (<85%)")) | K109: 13 | L109: 0 | M109: 33 | P109: 5 | Q109: 5 | R109: 0 | S109: 0 | T109: 0 | U109: 0 | V109: 0 | W109: 0 | X109: 1.8333333 | Y109: 1.8333333 | Z109: 1 | AA109: 1
A110: Mohamed HAMDANI | B110: 2026 | C110: 34 | D110: =B110&"-S"&TEXT(C110,"00") | E110: 9800223972_Fiche ZOOM Multiprojets CIC | F110: pdf | G110: 46256 | H110: RAPDF | I110: 100 | J110: =IF(I110="","À saisir",IF(I110>=85,"CONFORME (≥85%)","NON CONFORME (<85%)")) | K110: 14 | L110: 0 | M110: 32 | P110: 5 | Q110: 5 | R110: 0 | S110: 0 | T110: 0 | U110: 0 | V110: 0 | W110: 0 | X110: 1.8333333 | Y110: 1.8333333 | Z110: 1 | AA110: 1
A111: Hiba LISSAOUI | B111: 2026 | C111: 35 | D111: =B111&"-S"&TEXT(C111,"00") | E111: (à saisir) | H111: — | J111: =IF(I111="","À saisir",IF(I111>=85,"CONFORME (≥85%)","NON CONFORME (<85%)")) | P111: 0 | Q111: 0 | R111: 0 | S111: 0 | T111: 4 | U111: 1 | V111: 0 | W111: 0 | X111: 0 | Y111: 0
A112: Imad RMAIDI | B112: 2026 | C112: 35 | D112: =B112&"-S"&TEXT(C112,"00") | E112: IRD_9902030015_011000625586104 | F112: pdf | G112: 46259 | H112: RAPDF | I112: 100 | J112: =IF(I112="","À saisir",IF(I112>=85,"CONFORME (≥85%)","NON CONFORME (<85%)")) | K112: 18 | L112: 0 | M112: 28 | P112: 5 | Q112: 5 | R112: 0 | S112: 0 | T112: 0 | U112: 0 | V112: 0 | W112: 0 | X112: 1.8333333 | Y112: 1.8333333 | Z112: 1 | AA112: 1
...

Sheet Remarques
A1: Collaborateur | B1: Année | C1: Semaine | D1: Document | E1: Remarque
A2: Imad RMAIDI | B2: 2026 | C2: 11 | D2: SAN_9902020008_011000745243123 | E2: Document traité (fichiers présents) mais aucun rapport d'évaluation : note non renseignée.
A3: Mohamed HAMDANI | B3: 2026 | C3: 11 | D3: SAN_9902030053_011000789059347 | E3: Document traité (fichiers présents) mais aucun rapport d'évaluation : note non renseignée.
A4: Imad RMAIDI | B4: 2026 | C4: 12 | D4: (dossier vide) | E4: Dossier de la semaine créé mais vide : aucun document ni rapport.
A5: Hafssa BENCHRIF | B5: 2026 | C5: 16 | D5: 9800059279 Fc_E-Retrait_v062026 | E5: Document traité (fichiers présents) mais aucun rapport d'évaluation : note non renseignée.
A6: Hafssa BENCHRIF | B6: 2026 | C6: 17 | D6: (dossier vide) | E6: Dossier de la semaine créé mais vide : aucun document ni rapport.
A7: Mohamed HAMDANI | B7: 2026 | C7: 23 | D7: PEA _0140020765-Vadsf2026 | E7: Type de document « Non spécifié » dans le rapport : déduit du dossier (pdf).
A8: Hiba LISSAOUI | B8: 2026 | C8: 24 | D8: P1_Notice_Monabanq_10-2026 | E8: Dossier classé en S24 mais le rapport indique « Semaine 31 » (évalué le 2026-07-28) : semaine du dossier retenue.
A9: Hiba LISSAOUI | B9: 2026 | C9: 24 | D9: P1_Notice_Monabanq_10-2026 | E9: Type de document « Non spécifié » dans le rapport : déduit du dossier (pdf).
A10: Hiba LISSAOUI | B10: 2026 | C10: 25 | D10: 0130015514_FC Tonic Privilège à préavis_072026 | E10: Dossier classé en S25 mais le rapport indique « Semaine 31 » (évalué le 2026-07-28) : semaine du dossier retenue.
A11: Hiba LISSAOUI | B11: 2026 | C11: 25 | D11: 0130015514_FC Tonic Privilège à préavis_072026 | E11: Type de document « Non spécifié » dans le rapport : déduit du dossier (pdf).
A12: Mohamed HAMDANI | B12: 2026 | C12: 25 | D12: 0130018095_FC CM ADD_072026 | E12: Type de document « Non spécifié » dans le rapport : déduit du dossier (pdf).
A13: Mohamed HAMDANI | B13: 2026 | C13: 26 | D13: 0130009109 CM - Eurocompte jeune 072026 | E13: Type de document « Non spécifié » dans le rapport : déduit du dossier (pdf).
... A24: Hiba LISSAOUI | B24: 2026 | C24: 44 | D24: VIE_9902030044_011000541137492 | E24: Date d'évaluation (2026-10-29) postérieure à aujourd'hui : à vérifier.
